<?xml version="1.0" encoding="utf-8"?>
<annotation>
	<folder>--</folder>
	<filename>--</filename>
	<path>--</path>
	<source>
		<database>Unknown</database>
	</source>
	<size>
		<width>5184</width>
		<height>3456</height>
	</size>
	<segmented>3</segmented>
	<object>
		<name>WF</name>
		<pose>Unspecified</pose>
		<truncated>0</truncated>
		<difficult>0</difficult>
		<bndbox>
			<xmin>4017.0</xmin>
			<ymin>641.0</ymin>
			<xmax>4064.0</xmax>
			<ymax>691.0</ymax>
		</bndbox>
	</object>
	<object>
		<name>WF</name>
		<pose>Unspecified</pose>
		<truncated>0</truncated>
		<difficult>0</difficult>
		<bndbox>
			<xmin>4055.0</xmin>
			<ymin>601.0</ymin>
			<xmax>4114.0</xmax>
			<ymax>648.0</ymax>
		</bndbox>
	</object>
	<object>
		<name>WF</name>
		<pose>Unspecified</pose>
		<truncated>0</truncated>
		<difficult>0</difficult>
		<bndbox>
			<xmin>4101.0</xmin>
			<ymin>498.0</ymin>
			<xmax>4142.0</xmax>
			<ymax>544.0</ymax>
		</bndbox>
	</object>
	<object>
		<name>WF</name>
		<pose>Unspecified</pose>
		<truncated>0</truncated>
		<difficult>0</difficult>
		<bndbox>
			<xmin>4488.0</xmin>
			<ymin>798.0</ymin>
			<xmax>4531.0</xmax>
			<ymax>838.0</ymax>
		</bndbox>
	</object>
	<object>
		<name>WF</name>
		<pose>Unspecified</pose>
		<truncated>0</truncated>
		<difficult>0</difficult>
		<bndbox>
			<xmin>4658.0</xmin>
			<ymin>869.0</ymin>
			<xmax>4700.0</xmax>
			<ymax>912.0</ymax>
		</bndbox>
	</object>
	<object>
		<name>WF</name>
		<pose>Unspecified</pose>
		<truncated>0</truncated>
		<difficult>0</difficult>
		<bndbox>
			<xmin>4373.0</xmin>
			<ymin>1004.0</ymin>
			<xmax>4418.0</xmax>
			<ymax>1049.0</ymax>
		</bndbox>
	</object>
	<object>
		<name>WF</name>
		<pose>Unspecified</pose>
		<truncated>0</truncated>
		<difficult>0</difficult>
		<bndbox>
			<xmin>4344.0</xmin>
			<ymin>951.0</ymin>
			<xmax>4391.0</xmax>
			<ymax>991.0</ymax>
		</bndbox>
	</object>
	<object>
		<name>WF</name>
		<pose>Unspecified</pose>
		<truncated>0</truncated>
		<difficult>0</difficult>
		<bndbox>
			<xmin>4301.0</xmin>
			<ymin>1086.0</ymin>
			<xmax>4356.0</xmax>
			<ymax>1142.0</ymax>
		</bndbox>
	</object>
	<object>
		<name>WF</name>
		<pose>Unspecified</pose>
		<truncated>0</truncated>
		<difficult>0</difficult>
		<bndbox>
			<xmin>4243.0</xmin>
			<ymin>1165.0</ymin>
			<xmax>4298.0</xmax>
			<ymax>1217.0</ymax>
		</bndbox>
	</object>
	<object>
		<name>WF</name>
		<pose>Unspecified</pose>
		<truncated>0</truncated>
		<difficult>0</difficult>
		<bndbox>
			<xmin>4283.0</xmin>
			<ymin>1238.0</ymin>
			<xmax>4342.0</xmax>
			<ymax>1279.0</ymax>
		</bndbox>
	</object>
	<object>
		<name>WF</name>
		<pose>Unspecified</pose>
		<truncated>0</truncated>
		<difficult>0</difficult>
		<bndbox>
			<xmin>3807.0</xmin>
			<ymin>1358.0</ymin>
			<xmax>3870.0</xmax>
			<ymax>1415.0</ymax>
		</bndbox>
	</object>
	<object>
		<name>WF</name>
		<pose>Unspecified</pose>
		<truncated>0</truncated>
		<difficult>0</difficult>
		<bndbox>
			<xmin>3547.0</xmin>
			<ymin>1166.0</ymin>
			<xmax>3608.0</xmax>
			<ymax>1222.0</ymax>
		</bndbox>
	</object>
	<object>
		<name>WF</name>
		<pose>Unspecified</pose>
		<truncated>0</truncated>
		<difficult>0</difficult>
		<bndbox>
			<xmin>4256.0</xmin>
			<ymin>1609.0</ymin>
			<xmax>4315.0</xmax>
			<ymax>1658.0</ymax>
		</bndbox>
	</object>
	<object>
		<name>WF</name>
		<pose>Unspecified</pose>
		<truncated>0</truncated>
		<difficult>0</difficult>
		<bndbox>
			<xmin>4597.0</xmin>
			<ymin>956.0</ymin>
			<xmax>4645.0</xmax>
			<ymax>1000.0</ymax>
		</bndbox>
	</object>
	<object>
		<name>WF</name>
		<pose>Unspecified</pose>
		<truncated>0</truncated>
		<difficult>0</difficult>
		<bndbox>
			<xmin>4336.0</xmin>
			<ymin>1520.0</ymin>
			<xmax>4380.0</xmax>
			<ymax>1558.0</ymax>
		</bndbox>
	</object>
	<object>
		<name>WF</name>
		<pose>Unspecified</pose>
		<truncated>0</truncated>
		<difficult>0</difficult>
		<bndbox>
			<xmin>4534.0</xmin>
			<ymin>1672.0</ymin>
			<xmax>4572.0</xmax>
			<ymax>1706.0</ymax>
		</bndbox>
	</object>
	<object>
		<name>WF</name>
		<pose>Unspecified</pose>
		<truncated>0</truncated>
		<difficult>0</difficult>
		<bndbox>
			<xmin>4104.0</xmin>
			<ymin>1633.0</ymin>
			<xmax>4149.0</xmax>
			<ymax>1670.0</ymax>
		</bndbox>
	</object>
	<object>
		<name>WF</name>
		<pose>Unspecified</pose>
		<truncated>0</truncated>
		<difficult>0</difficult>
		<bndbox>
			<xmin>2706.0</xmin>
			<ymin>546.0</ymin>
			<xmax>2770.0</xmax>
			<ymax>602.0</ymax>
		</bndbox>
	</object>
	<object>
		<name>WF</name>
		<pose>Unspecified</pose>
		<truncated>0</truncated>
		<difficult>0</difficult>
		<bndbox>
			<xmin>2857.0</xmin>
			<ymin>672.0</ymin>
			<xmax>2914.0</xmax>
			<ymax>712.0</ymax>
		</bndbox>
	</object>
	<object>
		<name>WF</name>
		<pose>Unspecified</pose>
		<truncated>0</truncated>
		<difficult>0</difficult>
		<bndbox>
			<xmin>3197.0</xmin>
			<ymin>847.0</ymin>
			<xmax>3255.0</xmax>
			<ymax>892.0</ymax>
		</bndbox>
	</object>
	<object>
		<name>WF</name>
		<pose>Unspecified</pose>
		<truncated>0</truncated>
		<difficult>0</difficult>
		<bndbox>
			<xmin>2938.0</xmin>
			<ymin>903.0</ymin>
			<xmax>2981.0</xmax>
			<ymax>952.0</ymax>
		</bndbox>
	</object>
	<object>
		<name>WF</name>
		<pose>Unspecified</pose>
		<truncated>0</truncated>
		<difficult>0</difficult>
		<bndbox>
			<xmin>2730.0</xmin>
			<ymin>833.0</ymin>
			<xmax>2770.0</xmax>
			<ymax>881.0</ymax>
		</bndbox>
	</object>
	<object>
		<name>WF</name>
		<pose>Unspecified</pose>
		<truncated>0</truncated>
		<difficult>0</difficult>
		<bndbox>
			<xmin>2584.0</xmin>
			<ymin>847.0</ymin>
			<xmax>2629.0</xmax>
			<ymax>902.0</ymax>
		</bndbox>
	</object>
	<object>
		<name>WF</name>
		<pose>Unspecified</pose>
		<truncated>0</truncated>
		<difficult>0</difficult>
		<bndbox>
			<xmin>2449.0</xmin>
			<ymin>857.0</ymin>
			<xmax>2502.0</xmax>
			<ymax>902.0</ymax>
		</bndbox>
	</object>
	<object>
		<name>WF</name>
		<pose>Unspecified</pose>
		<truncated>0</truncated>
		<difficult>0</difficult>
		<bndbox>
			<xmin>2373.0</xmin>
			<ymin>527.0</ymin>
			<xmax>2429.0</xmax>
			<ymax>571.0</ymax>
		</bndbox>
	</object>
	<object>
		<name>WF</name>
		<pose>Unspecified</pose>
		<truncated>0</truncated>
		<difficult>0</difficult>
		<bndbox>
			<xmin>2314.0</xmin>
			<ymin>609.0</ymin>
			<xmax>2350.0</xmax>
			<ymax>648.0</ymax>
		</bndbox>
	</object>
	<object>
		<name>WF</name>
		<pose>Unspecified</pose>
		<truncated>0</truncated>
		<difficult>0</difficult>
		<bndbox>
			<xmin>2034.0</xmin>
			<ymin>653.0</ymin>
			<xmax>2109.0</xmax>
			<ymax>697.0</ymax>
		</bndbox>
	</object>
	<object>
		<name>WF</name>
		<pose>Unspecified</pose>
		<truncated>0</truncated>
		<difficult>0</difficult>
		<bndbox>
			<xmin>2906.0</xmin>
			<ymin>1307.0</ymin>
			<xmax>2959.0</xmax>
			<ymax>1353.0</ymax>
		</bndbox>
	</object>
	<object>
		<name>WF</name>
		<pose>Unspecified</pose>
		<truncated>0</truncated>
		<difficult>0</difficult>
		<bndbox>
			<xmin>2965.0</xmin>
			<ymin>1475.0</ymin>
			<xmax>3019.0</xmax>
			<ymax>1522.0</ymax>
		</bndbox>
	</object>
	<object>
		<name>WF</name>
		<pose>Unspecified</pose>
		<truncated>0</truncated>
		<difficult>0</difficult>
		<bndbox>
			<xmin>2502.0</xmin>
			<ymin>1411.0</ymin>
			<xmax>2557.0</xmax>
			<ymax>1463.0</ymax>
		</bndbox>
	</object>
	<object>
		<name>WF</name>
		<pose>Unspecified</pose>
		<truncated>0</truncated>
		<difficult>0</difficult>
		<bndbox>
			<xmin>2942.0</xmin>
			<ymin>1187.0</ymin>
			<xmax>2976.0</xmax>
			<ymax>1218.0</ymax>
		</bndbox>
	</object>
	<object>
		<name>WF</name>
		<pose>Unspecified</pose>
		<truncated>0</truncated>
		<difficult>0</difficult>
		<bndbox>
			<xmin>2423.0</xmin>
			<ymin>1092.0</ymin>
			<xmax>2480.0</xmax>
			<ymax>1132.0</ymax>
		</bndbox>
	</object>
	<object>
		<name>WF</name>
		<pose>Unspecified</pose>
		<truncated>0</truncated>
		<difficult>0</difficult>
		<bndbox>
			<xmin>2269.0</xmin>
			<ymin>1102.0</ymin>
			<xmax>2320.0</xmax>
			<ymax>1145.0</ymax>
		</bndbox>
	</object>
	<object>
		<name>WF</name>
		<pose>Unspecified</pose>
		<truncated>0</truncated>
		<difficult>0</difficult>
		<bndbox>
			<xmin>1994.0</xmin>
			<ymin>1131.0</ymin>
			<xmax>2064.0</xmax>
			<ymax>1181.0</ymax>
		</bndbox>
	</object>
	<object>
		<name>WF</name>
		<pose>Unspecified</pose>
		<truncated>0</truncated>
		<difficult>0</difficult>
		<bndbox>
			<xmin>2245.0</xmin>
			<ymin>723.0</ymin>
			<xmax>2310.0</xmax>
			<ymax>763.0</ymax>
		</bndbox>
	</object>
	<object>
		<name>WF</name>
		<pose>Unspecified</pose>
		<truncated>0</truncated>
		<difficult>0</difficult>
		<bndbox>
			<xmin>2789.0</xmin>
			<ymin>737.0</ymin>
			<xmax>2860.0</xmax>
			<ymax>779.0</ymax>
		</bndbox>
	</object>
	<object>
		<name>WF</name>
		<pose>Unspecified</pose>
		<truncated>0</truncated>
		<difficult>0</difficult>
		<bndbox>
			<xmin>2181.0</xmin>
			<ymin>759.0</ymin>
			<xmax>2224.0</xmax>
			<ymax>808.0</ymax>
		</bndbox>
	</object>
	<object>
		<name>WF</name>
		<pose>Unspecified</pose>
		<truncated>0</truncated>
		<difficult>0</difficult>
		<bndbox>
			<xmin>2063.0</xmin>
			<ymin>976.0</ymin>
			<xmax>2108.0</xmax>
			<ymax>1022.0</ymax>
		</bndbox>
	</object>
	<object>
		<name>WF</name>
		<pose>Unspecified</pose>
		<truncated>0</truncated>
		<difficult>0</difficult>
		<bndbox>
			<xmin>2058.0</xmin>
			<ymin>1045.0</ymin>
			<xmax>2101.0</xmax>
			<ymax>1086.0</ymax>
		</bndbox>
	</object>
	<object>
		<name>WF</name>
		<pose>Unspecified</pose>
		<truncated>0</truncated>
		<difficult>0</difficult>
		<bndbox>
			<xmin>1865.0</xmin>
			<ymin>1062.0</ymin>
			<xmax>1911.0</xmax>
			<ymax>1100.0</ymax>
		</bndbox>
	</object>
	<object>
		<name>WF</name>
		<pose>Unspecified</pose>
		<truncated>0</truncated>
		<difficult>0</difficult>
		<bndbox>
			<xmin>2245.0</xmin>
			<ymin>1396.0</ymin>
			<xmax>2302.0</xmax>
			<ymax>1440.0</ymax>
		</bndbox>
	</object>
	<object>
		<name>WF</name>
		<pose>Unspecified</pose>
		<truncated>0</truncated>
		<difficult>0</difficult>
		<bndbox>
			<xmin>1921.0</xmin>
			<ymin>1394.0</ymin>
			<xmax>1991.0</xmax>
			<ymax>1430.0</ymax>
		</bndbox>
	</object>
	<object>
		<name>WF</name>
		<pose>Unspecified</pose>
		<truncated>0</truncated>
		<difficult>0</difficult>
		<bndbox>
			<xmin>1807.0</xmin>
			<ymin>1304.0</ymin>
			<xmax>1870.0</xmax>
			<ymax>1344.0</ymax>
		</bndbox>
	</object>
	<object>
		<name>WF</name>
		<pose>Unspecified</pose>
		<truncated>0</truncated>
		<difficult>0</difficult>
		<bndbox>
			<xmin>2334.0</xmin>
			<ymin>1522.0</ymin>
			<xmax>2395.0</xmax>
			<ymax>1573.0</ymax>
		</bndbox>
	</object>
	<object>
		<name>WF</name>
		<pose>Unspecified</pose>
		<truncated>0</truncated>
		<difficult>0</difficult>
		<bndbox>
			<xmin>2839.0</xmin>
			<ymin>473.0</ymin>
			<xmax>2889.0</xmax>
			<ymax>512.0</ymax>
		</bndbox>
	</object>
	<object>
		<name>WF</name>
		<pose>Unspecified</pose>
		<truncated>0</truncated>
		<difficult>0</difficult>
		<bndbox>
			<xmin>3268.0</xmin>
			<ymin>1025.0</ymin>
			<xmax>3326.0</xmax>
			<ymax>1068.0</ymax>
		</bndbox>
	</object>
	<object>
		<name>WF</name>
		<pose>Unspecified</pose>
		<truncated>0</truncated>
		<difficult>0</difficult>
		<bndbox>
			<xmin>2907.0</xmin>
			<ymin>1683.0</ymin>
			<xmax>2945.0</xmax>
			<ymax>1706.0</ymax>
		</bndbox>
	</object>
	<object>
		<name>WF</name>
		<pose>Unspecified</pose>
		<truncated>0</truncated>
		<difficult>0</difficult>
		<bndbox>
			<xmin>1431.0</xmin>
			<ymin>489.0</ymin>
			<xmax>1472.0</xmax>
			<ymax>517.0</ymax>
		</bndbox>
	</object>
	<object>
		<name>WF</name>
		<pose>Unspecified</pose>
		<truncated>0</truncated>
		<difficult>0</difficult>
		<bndbox>
			<xmin>1472.0</xmin>
			<ymin>522.0</ymin>
			<xmax>1527.0</xmax>
			<ymax>564.0</ymax>
		</bndbox>
	</object>
	<object>
		<name>WF</name>
		<pose>Unspecified</pose>
		<truncated>0</truncated>
		<difficult>0</difficult>
		<bndbox>
			<xmin>1503.0</xmin>
			<ymin>589.0</ymin>
			<xmax>1553.0</xmax>
			<ymax>628.0</ymax>
		</bndbox>
	</object>
	<object>
		<name>WF</name>
		<pose>Unspecified</pose>
		<truncated>0</truncated>
		<difficult>0</difficult>
		<bndbox>
			<xmin>1637.0</xmin>
			<ymin>658.0</ymin>
			<xmax>1683.0</xmax>
			<ymax>703.0</ymax>
		</bndbox>
	</object>
	<object>
		<name>WF</name>
		<pose>Unspecified</pose>
		<truncated>0</truncated>
		<difficult>0</difficult>
		<bndbox>
			<xmin>1628.0</xmin>
			<ymin>789.0</ymin>
			<xmax>1674.0</xmax>
			<ymax>827.0</ymax>
		</bndbox>
	</object>
	<object>
		<name>WF</name>
		<pose>Unspecified</pose>
		<truncated>0</truncated>
		<difficult>0</difficult>
		<bndbox>
			<xmin>1613.0</xmin>
			<ymin>863.0</ymin>
			<xmax>1663.0</xmax>
			<ymax>903.0</ymax>
		</bndbox>
	</object>
	<object>
		<name>WF</name>
		<pose>Unspecified</pose>
		<truncated>0</truncated>
		<difficult>0</difficult>
		<bndbox>
			<xmin>1652.0</xmin>
			<ymin>952.0</ymin>
			<xmax>1703.0</xmax>
			<ymax>989.0</ymax>
		</bndbox>
	</object>
	<object>
		<name>WF</name>
		<pose>Unspecified</pose>
		<truncated>0</truncated>
		<difficult>0</difficult>
		<bndbox>
			<xmin>1579.0</xmin>
			<ymin>1036.0</ymin>
			<xmax>1630.0</xmax>
			<ymax>1093.0</ymax>
		</bndbox>
	</object>
	<object>
		<name>WF</name>
		<pose>Unspecified</pose>
		<truncated>0</truncated>
		<difficult>0</difficult>
		<bndbox>
			<xmin>1486.0</xmin>
			<ymin>896.0</ymin>
			<xmax>1547.0</xmax>
			<ymax>942.0</ymax>
		</bndbox>
	</object>
	<object>
		<name>WF</name>
		<pose>Unspecified</pose>
		<truncated>0</truncated>
		<difficult>0</difficult>
		<bndbox>
			<xmin>1133.0</xmin>
			<ymin>1220.0</ymin>
			<xmax>1194.0</xmax>
			<ymax>1263.0</ymax>
		</bndbox>
	</object>
	<object>
		<name>WF</name>
		<pose>Unspecified</pose>
		<truncated>0</truncated>
		<difficult>0</difficult>
		<bndbox>
			<xmin>1183.0</xmin>
			<ymin>1404.0</ymin>
			<xmax>1241.0</xmax>
			<ymax>1445.0</ymax>
		</bndbox>
	</object>
	<object>
		<name>WF</name>
		<pose>Unspecified</pose>
		<truncated>0</truncated>
		<difficult>0</difficult>
		<bndbox>
			<xmin>1316.0</xmin>
			<ymin>1587.0</ymin>
			<xmax>1375.0</xmax>
			<ymax>1631.0</ymax>
		</bndbox>
	</object>
	<object>
		<name>WF</name>
		<pose>Unspecified</pose>
		<truncated>0</truncated>
		<difficult>0</difficult>
		<bndbox>
			<xmin>1690.0</xmin>
			<ymin>1452.0</ymin>
			<xmax>1726.0</xmax>
			<ymax>1493.0</ymax>
		</bndbox>
	</object>
	<object>
		<name>WF</name>
		<pose>Unspecified</pose>
		<truncated>0</truncated>
		<difficult>0</difficult>
		<bndbox>
			<xmin>1106.0</xmin>
			<ymin>1520.0</ymin>
			<xmax>1158.0</xmax>
			<ymax>1553.0</ymax>
		</bndbox>
	</object>
	<object>
		<name>WF</name>
		<pose>Unspecified</pose>
		<truncated>0</truncated>
		<difficult>0</difficult>
		<bndbox>
			<xmin>1097.0</xmin>
			<ymin>1559.0</ymin>
			<xmax>1148.0</xmax>
			<ymax>1597.0</ymax>
		</bndbox>
	</object>
	<object>
		<name>WF</name>
		<pose>Unspecified</pose>
		<truncated>0</truncated>
		<difficult>0</difficult>
		<bndbox>
			<xmin>1020.0</xmin>
			<ymin>926.0</ymin>
			<xmax>1079.0</xmax>
			<ymax>983.0</ymax>
		</bndbox>
	</object>
	<object>
		<name>WF</name>
		<pose>Unspecified</pose>
		<truncated>0</truncated>
		<difficult>0</difficult>
		<bndbox>
			<xmin>825.0</xmin>
			<ymin>742.0</ymin>
			<xmax>883.0</xmax>
			<ymax>791.0</ymax>
		</bndbox>
	</object>
	<object>
		<name>WF</name>
		<pose>Unspecified</pose>
		<truncated>0</truncated>
		<difficult>0</difficult>
		<bndbox>
			<xmin>1083.0</xmin>
			<ymin>501.0</ymin>
			<xmax>1123.0</xmax>
			<ymax>539.0</ymax>
		</bndbox>
	</object>
	<object>
		<name>WF</name>
		<pose>Unspecified</pose>
		<truncated>0</truncated>
		<difficult>0</difficult>
		<bndbox>
			<xmin>1131.0</xmin>
			<ymin>619.0</ymin>
			<xmax>1185.0</xmax>
			<ymax>652.0</ymax>
		</bndbox>
	</object>
	<object>
		<name>WF</name>
		<pose>Unspecified</pose>
		<truncated>0</truncated>
		<difficult>0</difficult>
		<bndbox>
			<xmin>394.0</xmin>
			<ymin>581.0</ymin>
			<xmax>460.0</xmax>
			<ymax>622.0</ymax>
		</bndbox>
	</object>
	<object>
		<name>WF</name>
		<pose>Unspecified</pose>
		<truncated>0</truncated>
		<difficult>0</difficult>
		<bndbox>
			<xmin>202.0</xmin>
			<ymin>688.0</ymin>
			<xmax>260.0</xmax>
			<ymax>731.0</ymax>
		</bndbox>
	</object>
	<object>
		<name>WF</name>
		<pose>Unspecified</pose>
		<truncated>0</truncated>
		<difficult>0</difficult>
		<bndbox>
			<xmin>61.0</xmin>
			<ymin>711.0</ymin>
			<xmax>109.0</xmax>
			<ymax>758.0</ymax>
		</bndbox>
	</object>
	<object>
		<name>WF</name>
		<pose>Unspecified</pose>
		<truncated>0</truncated>
		<difficult>0</difficult>
		<bndbox>
			<xmin>319.0</xmin>
			<ymin>879.0</ymin>
			<xmax>373.0</xmax>
			<ymax>917.0</ymax>
		</bndbox>
	</object>
	<object>
		<name>WF</name>
		<pose>Unspecified</pose>
		<truncated>0</truncated>
		<difficult>0</difficult>
		<bndbox>
			<xmin>497.0</xmin>
			<ymin>1130.0</ymin>
			<xmax>545.0</xmax>
			<ymax>1169.0</ymax>
		</bndbox>
	</object>
	<object>
		<name>WF</name>
		<pose>Unspecified</pose>
		<truncated>0</truncated>
		<difficult>0</difficult>
		<bndbox>
			<xmin>194.0</xmin>
			<ymin>1162.0</ymin>
			<xmax>263.0</xmax>
			<ymax>1225.0</ymax>
		</bndbox>
	</object>
	<object>
		<name>WF</name>
		<pose>Unspecified</pose>
		<truncated>0</truncated>
		<difficult>0</difficult>
		<bndbox>
			<xmin>742.0</xmin>
			<ymin>1485.0</ymin>
			<xmax>786.0</xmax>
			<ymax>1547.0</ymax>
		</bndbox>
	</object>
	<object>
		<name>WF</name>
		<pose>Unspecified</pose>
		<truncated>0</truncated>
		<difficult>0</difficult>
		<bndbox>
			<xmin>495.0</xmin>
			<ymin>1491.0</ymin>
			<xmax>544.0</xmax>
			<ymax>1543.0</ymax>
		</bndbox>
	</object>
	<object>
		<name>WF</name>
		<pose>Unspecified</pose>
		<truncated>0</truncated>
		<difficult>0</difficult>
		<bndbox>
			<xmin>331.0</xmin>
			<ymin>1412.0</ymin>
			<xmax>378.0</xmax>
			<ymax>1447.0</ymax>
		</bndbox>
	</object>
	<object>
		<name>WF</name>
		<pose>Unspecified</pose>
		<truncated>0</truncated>
		<difficult>0</difficult>
		<bndbox>
			<xmin>283.0</xmin>
			<ymin>1439.0</ymin>
			<xmax>333.0</xmax>
			<ymax>1476.0</ymax>
		</bndbox>
	</object>
	<object>
		<name>WF</name>
		<pose>Unspecified</pose>
		<truncated>0</truncated>
		<difficult>0</difficult>
		<bndbox>
			<xmin>99.0</xmin>
			<ymin>1441.0</ymin>
			<xmax>162.0</xmax>
			<ymax>1484.0</ymax>
		</bndbox>
	</object>
	<object>
		<name>WF</name>
		<pose>Unspecified</pose>
		<truncated>0</truncated>
		<difficult>0</difficult>
		<bndbox>
			<xmin>144.0</xmin>
			<ymin>1500.0</ymin>
			<xmax>192.0</xmax>
			<ymax>1548.0</ymax>
		</bndbox>
	</object>
	<object>
		<name>WF</name>
		<pose>Unspecified</pose>
		<truncated>0</truncated>
		<difficult>0</difficult>
		<bndbox>
			<xmin>451.0</xmin>
			<ymin>1620.0</ymin>
			<xmax>498.0</xmax>
			<ymax>1672.0</ymax>
		</bndbox>
	</object>
	<object>
		<name>WF</name>
		<pose>Unspecified</pose>
		<truncated>0</truncated>
		<difficult>0</difficult>
		<bndbox>
			<xmin>636.0</xmin>
			<ymin>1553.0</ymin>
			<xmax>675.0</xmax>
			<ymax>1591.0</ymax>
		</bndbox>
	</object>
	<object>
		<name>WF</name>
		<pose>Unspecified</pose>
		<truncated>0</truncated>
		<difficult>0</difficult>
		<bndbox>
			<xmin>1410.0</xmin>
			<ymin>938.0</ymin>
			<xmax>1467.0</xmax>
			<ymax>993.0</ymax>
		</bndbox>
	</object>
	<object>
		<name>WF</name>
		<pose>Unspecified</pose>
		<truncated>0</truncated>
		<difficult>0</difficult>
		<bndbox>
			<xmin>363.0</xmin>
			<ymin>909.0</ymin>
			<xmax>409.0</xmax>
			<ymax>948.0</ymax>
		</bndbox>
	</object>
	<object>
		<name>WF</name>
		<pose>Unspecified</pose>
		<truncated>0</truncated>
		<difficult>0</difficult>
		<bndbox>
			<xmin>1118.0</xmin>
			<ymin>1075.0</ymin>
			<xmax>1177.0</xmax>
			<ymax>1120.0</ymax>
		</bndbox>
	</object>
	<object>
		<name>WF</name>
		<pose>Unspecified</pose>
		<truncated>0</truncated>
		<difficult>0</difficult>
		<bndbox>
			<xmin>4469.0</xmin>
			<ymin>1754.0</ymin>
			<xmax>4518.0</xmax>
			<ymax>1793.0</ymax>
		</bndbox>
	</object>
	<object>
		<name>WF</name>
		<pose>Unspecified</pose>
		<truncated>0</truncated>
		<difficult>0</difficult>
		<bndbox>
			<xmin>4398.0</xmin>
			<ymin>1706.0</ymin>
			<xmax>4438.0</xmax>
			<ymax>1744.0</ymax>
		</bndbox>
	</object>
	<object>
		<name>WF</name>
		<pose>Unspecified</pose>
		<truncated>0</truncated>
		<difficult>0</difficult>
		<bndbox>
			<xmin>4345.0</xmin>
			<ymin>1777.0</ymin>
			<xmax>4391.0</xmax>
			<ymax>1820.0</ymax>
		</bndbox>
	</object>
	<object>
		<name>WF</name>
		<pose>Unspecified</pose>
		<truncated>0</truncated>
		<difficult>0</difficult>
		<bndbox>
			<xmin>4492.0</xmin>
			<ymin>1898.0</ymin>
			<xmax>4539.0</xmax>
			<ymax>1942.0</ymax>
		</bndbox>
	</object>
	<object>
		<name>WF</name>
		<pose>Unspecified</pose>
		<truncated>0</truncated>
		<difficult>0</difficult>
		<bndbox>
			<xmin>4603.0</xmin>
			<ymin>2051.0</ymin>
			<xmax>4655.0</xmax>
			<ymax>2103.0</ymax>
		</bndbox>
	</object>
	<object>
		<name>WF</name>
		<pose>Unspecified</pose>
		<truncated>0</truncated>
		<difficult>0</difficult>
		<bndbox>
			<xmin>4745.0</xmin>
			<ymin>2273.0</ymin>
			<xmax>4792.0</xmax>
			<ymax>2316.0</ymax>
		</bndbox>
	</object>
	<object>
		<name>WF</name>
		<pose>Unspecified</pose>
		<truncated>0</truncated>
		<difficult>0</difficult>
		<bndbox>
			<xmin>4757.0</xmin>
			<ymin>2341.0</ymin>
			<xmax>4803.0</xmax>
			<ymax>2381.0</ymax>
		</bndbox>
	</object>
	<object>
		<name>WF</name>
		<pose>Unspecified</pose>
		<truncated>0</truncated>
		<difficult>0</difficult>
		<bndbox>
			<xmin>4543.0</xmin>
			<ymin>2368.0</ymin>
			<xmax>4600.0</xmax>
			<ymax>2414.0</ymax>
		</bndbox>
	</object>
	<object>
		<name>WF</name>
		<pose>Unspecified</pose>
		<truncated>0</truncated>
		<difficult>0</difficult>
		<bndbox>
			<xmin>4537.0</xmin>
			<ymin>2485.0</ymin>
			<xmax>4577.0</xmax>
			<ymax>2512.0</ymax>
		</bndbox>
	</object>
	<object>
		<name>WF</name>
		<pose>Unspecified</pose>
		<truncated>0</truncated>
		<difficult>0</difficult>
		<bndbox>
			<xmin>4508.0</xmin>
			<ymin>2503.0</ymin>
			<xmax>4551.0</xmax>
			<ymax>2539.0</ymax>
		</bndbox>
	</object>
	<object>
		<name>WF</name>
		<pose>Unspecified</pose>
		<truncated>0</truncated>
		<difficult>0</difficult>
		<bndbox>
			<xmin>4359.0</xmin>
			<ymin>2363.0</ymin>
			<xmax>4406.0</xmax>
			<ymax>2421.0</ymax>
		</bndbox>
	</object>
	<object>
		<name>WF</name>
		<pose>Unspecified</pose>
		<truncated>0</truncated>
		<difficult>0</difficult>
		<bndbox>
			<xmin>4516.0</xmin>
			<ymin>2300.0</ymin>
			<xmax>4572.0</xmax>
			<ymax>2349.0</ymax>
		</bndbox>
	</object>
	<object>
		<name>WF</name>
		<pose>Unspecified</pose>
		<truncated>0</truncated>
		<difficult>0</difficult>
		<bndbox>
			<xmin>4603.0</xmin>
			<ymin>2233.0</ymin>
			<xmax>4656.0</xmax>
			<ymax>2279.0</ymax>
		</bndbox>
	</object>
	<object>
		<name>WF</name>
		<pose>Unspecified</pose>
		<truncated>0</truncated>
		<difficult>0</difficult>
		<bndbox>
			<xmin>4081.0</xmin>
			<ymin>2463.0</ymin>
			<xmax>4140.0</xmax>
			<ymax>2504.0</ymax>
		</bndbox>
	</object>
	<object>
		<name>WF</name>
		<pose>Unspecified</pose>
		<truncated>0</truncated>
		<difficult>0</difficult>
		<bndbox>
			<xmin>4033.0</xmin>
			<ymin>2464.0</ymin>
			<xmax>4070.0</xmax>
			<ymax>2515.0</ymax>
		</bndbox>
	</object>
	<object>
		<name>WF</name>
		<pose>Unspecified</pose>
		<truncated>0</truncated>
		<difficult>0</difficult>
		<bndbox>
			<xmin>3958.0</xmin>
			<ymin>2469.0</ymin>
			<xmax>4008.0</xmax>
			<ymax>2533.0</ymax>
		</bndbox>
	</object>
	<object>
		<name>WF</name>
		<pose>Unspecified</pose>
		<truncated>0</truncated>
		<difficult>0</difficult>
		<bndbox>
			<xmin>4722.0</xmin>
			<ymin>2680.0</ymin>
			<xmax>4776.0</xmax>
			<ymax>2706.0</ymax>
		</bndbox>
	</object>
	<object>
		<name>WF</name>
		<pose>Unspecified</pose>
		<truncated>0</truncated>
		<difficult>0</difficult>
		<bndbox>
			<xmin>4833.0</xmin>
			<ymin>2731.0</ymin>
			<xmax>4881.0</xmax>
			<ymax>2765.0</ymax>
		</bndbox>
	</object>
	<object>
		<name>WF</name>
		<pose>Unspecified</pose>
		<truncated>0</truncated>
		<difficult>0</difficult>
		<bndbox>
			<xmin>4888.0</xmin>
			<ymin>2781.0</ymin>
			<xmax>4922.0</xmax>
			<ymax>2816.0</ymax>
		</bndbox>
	</object>
	<object>
		<name>WF</name>
		<pose>Unspecified</pose>
		<truncated>0</truncated>
		<difficult>0</difficult>
		<bndbox>
			<xmin>4731.0</xmin>
			<ymin>2744.0</ymin>
			<xmax>4777.0</xmax>
			<ymax>2786.0</ymax>
		</bndbox>
	</object>
	<object>
		<name>WF</name>
		<pose>Unspecified</pose>
		<truncated>0</truncated>
		<difficult>0</difficult>
		<bndbox>
			<xmin>4667.0</xmin>
			<ymin>2719.0</ymin>
			<xmax>4705.0</xmax>
			<ymax>2748.0</ymax>
		</bndbox>
	</object>
	<object>
		<name>WF</name>
		<pose>Unspecified</pose>
		<truncated>0</truncated>
		<difficult>0</difficult>
		<bndbox>
			<xmin>4635.0</xmin>
			<ymin>2725.0</ymin>
			<xmax>4672.0</xmax>
			<ymax>2758.0</ymax>
		</bndbox>
	</object>
	<object>
		<name>WF</name>
		<pose>Unspecified</pose>
		<truncated>0</truncated>
		<difficult>0</difficult>
		<bndbox>
			<xmin>4564.0</xmin>
			<ymin>2660.0</ymin>
			<xmax>4606.0</xmax>
			<ymax>2712.0</ymax>
		</bndbox>
	</object>
	<object>
		<name>WF</name>
		<pose>Unspecified</pose>
		<truncated>0</truncated>
		<difficult>0</difficult>
		<bndbox>
			<xmin>4585.0</xmin>
			<ymin>2599.0</ymin>
			<xmax>4634.0</xmax>
			<ymax>2641.0</ymax>
		</bndbox>
	</object>
	<object>
		<name>WF</name>
		<pose>Unspecified</pose>
		<truncated>0</truncated>
		<difficult>0</difficult>
		<bndbox>
			<xmin>4357.0</xmin>
			<ymin>1936.0</ymin>
			<xmax>4399.0</xmax>
			<ymax>1991.0</ymax>
		</bndbox>
	</object>
	<object>
		<name>WF</name>
		<pose>Unspecified</pose>
		<truncated>0</truncated>
		<difficult>0</difficult>
		<bndbox>
			<xmin>4148.0</xmin>
			<ymin>1870.0</ymin>
			<xmax>4211.0</xmax>
			<ymax>1925.0</ymax>
		</bndbox>
	</object>
	<object>
		<name>WF</name>
		<pose>Unspecified</pose>
		<truncated>0</truncated>
		<difficult>0</difficult>
		<bndbox>
			<xmin>4170.0</xmin>
			<ymin>1929.0</ymin>
			<xmax>4220.0</xmax>
			<ymax>1975.0</ymax>
		</bndbox>
	</object>
	<object>
		<name>WF</name>
		<pose>Unspecified</pose>
		<truncated>0</truncated>
		<difficult>0</difficult>
		<bndbox>
			<xmin>4229.0</xmin>
			<ymin>2021.0</ymin>
			<xmax>4270.0</xmax>
			<ymax>2069.0</ymax>
		</bndbox>
	</object>
	<object>
		<name>WF</name>
		<pose>Unspecified</pose>
		<truncated>0</truncated>
		<difficult>0</difficult>
		<bndbox>
			<xmin>3994.0</xmin>
			<ymin>2279.0</ymin>
			<xmax>4045.0</xmax>
			<ymax>2323.0</ymax>
		</bndbox>
	</object>
	<object>
		<name>WF</name>
		<pose>Unspecified</pose>
		<truncated>0</truncated>
		<difficult>0</difficult>
		<bndbox>
			<xmin>3780.0</xmin>
			<ymin>2340.0</ymin>
			<xmax>3844.0</xmax>
			<ymax>2394.0</ymax>
		</bndbox>
	</object>
	<object>
		<name>WF</name>
		<pose>Unspecified</pose>
		<truncated>0</truncated>
		<difficult>0</difficult>
		<bndbox>
			<xmin>3778.0</xmin>
			<ymin>1942.0</ymin>
			<xmax>3826.0</xmax>
			<ymax>1984.0</ymax>
		</bndbox>
	</object>
	<object>
		<name>WF</name>
		<pose>Unspecified</pose>
		<truncated>0</truncated>
		<difficult>0</difficult>
		<bndbox>
			<xmin>3882.0</xmin>
			<ymin>1731.0</ymin>
			<xmax>3931.0</xmax>
			<ymax>1780.0</ymax>
		</bndbox>
	</object>
	<object>
		<name>WF</name>
		<pose>Unspecified</pose>
		<truncated>0</truncated>
		<difficult>0</difficult>
		<bndbox>
			<xmin>3807.0</xmin>
			<ymin>1706.0</ymin>
			<xmax>3849.0</xmax>
			<ymax>1729.0</ymax>
		</bndbox>
	</object>
	<object>
		<name>WF</name>
		<pose>Unspecified</pose>
		<truncated>0</truncated>
		<difficult>0</difficult>
		<bndbox>
			<xmin>3813.0</xmin>
			<ymin>2021.0</ymin>
			<xmax>3857.0</xmax>
			<ymax>2084.0</ymax>
		</bndbox>
	</object>
	<object>
		<name>WF</name>
		<pose>Unspecified</pose>
		<truncated>0</truncated>
		<difficult>0</difficult>
		<bndbox>
			<xmin>4455.0</xmin>
			<ymin>2558.0</ymin>
			<xmax>4491.0</xmax>
			<ymax>2598.0</ymax>
		</bndbox>
	</object>
	<object>
		<name>WF</name>
		<pose>Unspecified</pose>
		<truncated>0</truncated>
		<difficult>0</difficult>
		<bndbox>
			<xmin>4199.0</xmin>
			<ymin>2519.0</ymin>
			<xmax>4238.0</xmax>
			<ymax>2546.0</ymax>
		</bndbox>
	</object>
	<object>
		<name>WF</name>
		<pose>Unspecified</pose>
		<truncated>0</truncated>
		<difficult>0</difficult>
		<bndbox>
			<xmin>4328.0</xmin>
			<ymin>2679.0</ymin>
			<xmax>4377.0</xmax>
			<ymax>2727.0</ymax>
		</bndbox>
	</object>
	<object>
		<name>WF</name>
		<pose>Unspecified</pose>
		<truncated>0</truncated>
		<difficult>0</difficult>
		<bndbox>
			<xmin>4433.0</xmin>
			<ymin>2728.0</ymin>
			<xmax>4466.0</xmax>
			<ymax>2773.0</ymax>
		</bndbox>
	</object>
	<object>
		<name>WF</name>
		<pose>Unspecified</pose>
		<truncated>0</truncated>
		<difficult>0</difficult>
		<bndbox>
			<xmin>4473.0</xmin>
			<ymin>2767.0</ymin>
			<xmax>4534.0</xmax>
			<ymax>2809.0</ymax>
		</bndbox>
	</object>
	<object>
		<name>WF</name>
		<pose>Unspecified</pose>
		<truncated>0</truncated>
		<difficult>0</difficult>
		<bndbox>
			<xmin>4155.0</xmin>
			<ymin>2697.0</ymin>
			<xmax>4192.0</xmax>
			<ymax>2739.0</ymax>
		</bndbox>
	</object>
	<object>
		<name>WF</name>
		<pose>Unspecified</pose>
		<truncated>0</truncated>
		<difficult>0</difficult>
		<bndbox>
			<xmin>4120.0</xmin>
			<ymin>2651.0</ymin>
			<xmax>4175.0</xmax>
			<ymax>2695.0</ymax>
		</bndbox>
	</object>
	<object>
		<name>WF</name>
		<pose>Unspecified</pose>
		<truncated>0</truncated>
		<difficult>0</difficult>
		<bndbox>
			<xmin>3664.0</xmin>
			<ymin>2559.0</ymin>
			<xmax>3716.0</xmax>
			<ymax>2600.0</ymax>
		</bndbox>
	</object>
	<object>
		<name>WF</name>
		<pose>Unspecified</pose>
		<truncated>0</truncated>
		<difficult>0</difficult>
		<bndbox>
			<xmin>3862.0</xmin>
			<ymin>2533.0</ymin>
			<xmax>3901.0</xmax>
			<ymax>2570.0</ymax>
		</bndbox>
	</object>
	<object>
		<name>WF</name>
		<pose>Unspecified</pose>
		<truncated>0</truncated>
		<difficult>0</difficult>
		<bndbox>
			<xmin>3551.0</xmin>
			<ymin>1826.0</ymin>
			<xmax>3586.0</xmax>
			<ymax>1868.0</ymax>
		</bndbox>
	</object>
	<object>
		<name>WF</name>
		<pose>Unspecified</pose>
		<truncated>0</truncated>
		<difficult>0</difficult>
		<bndbox>
			<xmin>3537.0</xmin>
			<ymin>1904.0</ymin>
			<xmax>3578.0</xmax>
			<ymax>1948.0</ymax>
		</bndbox>
	</object>
	<object>
		<name>WF</name>
		<pose>Unspecified</pose>
		<truncated>0</truncated>
		<difficult>0</difficult>
		<bndbox>
			<xmin>3572.0</xmin>
			<ymin>2008.0</ymin>
			<xmax>3620.0</xmax>
			<ymax>2051.0</ymax>
		</bndbox>
	</object>
	<object>
		<name>WF</name>
		<pose>Unspecified</pose>
		<truncated>0</truncated>
		<difficult>0</difficult>
		<bndbox>
			<xmin>3618.0</xmin>
			<ymin>2414.0</ymin>
			<xmax>3680.0</xmax>
			<ymax>2467.0</ymax>
		</bndbox>
	</object>
	<object>
		<name>WF</name>
		<pose>Unspecified</pose>
		<truncated>0</truncated>
		<difficult>0</difficult>
		<bndbox>
			<xmin>3745.0</xmin>
			<ymin>2655.0</ymin>
			<xmax>3787.0</xmax>
			<ymax>2692.0</ymax>
		</bndbox>
	</object>
	<object>
		<name>WF</name>
		<pose>Unspecified</pose>
		<truncated>0</truncated>
		<difficult>0</difficult>
		<bndbox>
			<xmin>3552.0</xmin>
			<ymin>2874.0</ymin>
			<xmax>3592.0</xmax>
			<ymax>2912.0</ymax>
		</bndbox>
	</object>
	<object>
		<name>WF</name>
		<pose>Unspecified</pose>
		<truncated>0</truncated>
		<difficult>0</difficult>
		<bndbox>
			<xmin>3671.0</xmin>
			<ymin>2833.0</ymin>
			<xmax>3709.0</xmax>
			<ymax>2873.0</ymax>
		</bndbox>
	</object>
	<object>
		<name>WF</name>
		<pose>Unspecified</pose>
		<truncated>0</truncated>
		<difficult>0</difficult>
		<bndbox>
			<xmin>3603.0</xmin>
			<ymin>1809.0</ymin>
			<xmax>3645.0</xmax>
			<ymax>1845.0</ymax>
		</bndbox>
	</object>
	<object>
		<name>WF</name>
		<pose>Unspecified</pose>
		<truncated>0</truncated>
		<difficult>0</difficult>
		<bndbox>
			<xmin>3729.0</xmin>
			<ymin>1929.0</ymin>
			<xmax>3770.0</xmax>
			<ymax>1975.0</ymax>
		</bndbox>
	</object>
	<object>
		<name>WF</name>
		<pose>Unspecified</pose>
		<truncated>0</truncated>
		<difficult>0</difficult>
		<bndbox>
			<xmin>4346.0</xmin>
			<ymin>2230.0</ymin>
			<xmax>4403.0</xmax>
			<ymax>2303.0</ymax>
		</bndbox>
	</object>
	<object>
		<name>WF</name>
		<pose>Unspecified</pose>
		<truncated>0</truncated>
		<difficult>0</difficult>
		<bndbox>
			<xmin>4282.0</xmin>
			<ymin>2384.0</ymin>
			<xmax>4338.0</xmax>
			<ymax>2423.0</ymax>
		</bndbox>
	</object>
	<object>
		<name>WF</name>
		<pose>Unspecified</pose>
		<truncated>0</truncated>
		<difficult>0</difficult>
		<bndbox>
			<xmin>4415.0</xmin>
			<ymin>2438.0</ymin>
			<xmax>4469.0</xmax>
			<ymax>2483.0</ymax>
		</bndbox>
	</object>
	<object>
		<name>WF</name>
		<pose>Unspecified</pose>
		<truncated>0</truncated>
		<difficult>0</difficult>
		<bndbox>
			<xmin>4564.0</xmin>
			<ymin>2407.0</ymin>
			<xmax>4611.0</xmax>
			<ymax>2456.0</ymax>
		</bndbox>
	</object>
	<object>
		<name>WF</name>
		<pose>Unspecified</pose>
		<truncated>0</truncated>
		<difficult>0</difficult>
		<bndbox>
			<xmin>4343.0</xmin>
			<ymin>2640.0</ymin>
			<xmax>4383.0</xmax>
			<ymax>2686.0</ymax>
		</bndbox>
	</object>
	<object>
		<name>WF</name>
		<pose>Unspecified</pose>
		<truncated>0</truncated>
		<difficult>0</difficult>
		<bndbox>
			<xmin>4157.0</xmin>
			<ymin>2507.0</ymin>
			<xmax>4201.0</xmax>
			<ymax>2540.0</ymax>
		</bndbox>
	</object>
	<object>
		<name>WF</name>
		<pose>Unspecified</pose>
		<truncated>0</truncated>
		<difficult>0</difficult>
		<bndbox>
			<xmin>3398.0</xmin>
			<ymin>1755.0</ymin>
			<xmax>3440.0</xmax>
			<ymax>1811.0</ymax>
		</bndbox>
	</object>
	<object>
		<name>WF</name>
		<pose>Unspecified</pose>
		<truncated>0</truncated>
		<difficult>0</difficult>
		<bndbox>
			<xmin>3197.0</xmin>
			<ymin>2108.0</ymin>
			<xmax>3245.0</xmax>
			<ymax>2162.0</ymax>
		</bndbox>
	</object>
	<object>
		<name>WF</name>
		<pose>Unspecified</pose>
		<truncated>0</truncated>
		<difficult>0</difficult>
		<bndbox>
			<xmin>2845.0</xmin>
			<ymin>2064.0</ymin>
			<xmax>2875.0</xmax>
			<ymax>2116.0</ymax>
		</bndbox>
	</object>
	<object>
		<name>WF</name>
		<pose>Unspecified</pose>
		<truncated>0</truncated>
		<difficult>0</difficult>
		<bndbox>
			<xmin>2734.0</xmin>
			<ymin>2141.0</ymin>
			<xmax>2761.0</xmax>
			<ymax>2176.0</ymax>
		</bndbox>
	</object>
	<object>
		<name>WF</name>
		<pose>Unspecified</pose>
		<truncated>0</truncated>
		<difficult>0</difficult>
		<bndbox>
			<xmin>2239.0</xmin>
			<ymin>1885.0</ymin>
			<xmax>2297.0</xmax>
			<ymax>1920.0</ymax>
		</bndbox>
	</object>
	<object>
		<name>WF</name>
		<pose>Unspecified</pose>
		<truncated>0</truncated>
		<difficult>0</difficult>
		<bndbox>
			<xmin>2006.0</xmin>
			<ymin>1805.0</ymin>
			<xmax>2060.0</xmax>
			<ymax>1853.0</ymax>
		</bndbox>
	</object>
	<object>
		<name>WF</name>
		<pose>Unspecified</pose>
		<truncated>0</truncated>
		<difficult>0</difficult>
		<bndbox>
			<xmin>2488.0</xmin>
			<ymin>2150.0</ymin>
			<xmax>2558.0</xmax>
			<ymax>2186.0</ymax>
		</bndbox>
	</object>
	<object>
		<name>WF</name>
		<pose>Unspecified</pose>
		<truncated>0</truncated>
		<difficult>0</difficult>
		<bndbox>
			<xmin>2958.0</xmin>
			<ymin>2206.0</ymin>
			<xmax>3025.0</xmax>
			<ymax>2251.0</ymax>
		</bndbox>
	</object>
	<object>
		<name>WF</name>
		<pose>Unspecified</pose>
		<truncated>0</truncated>
		<difficult>0</difficult>
		<bndbox>
			<xmin>2717.0</xmin>
			<ymin>2261.0</ymin>
			<xmax>2787.0</xmax>
			<ymax>2303.0</ymax>
		</bndbox>
	</object>
	<object>
		<name>WF</name>
		<pose>Unspecified</pose>
		<truncated>0</truncated>
		<difficult>0</difficult>
		<bndbox>
			<xmin>2589.0</xmin>
			<ymin>2214.0</ymin>
			<xmax>2639.0</xmax>
			<ymax>2233.0</ymax>
		</bndbox>
	</object>
	<object>
		<name>WF</name>
		<pose>Unspecified</pose>
		<truncated>0</truncated>
		<difficult>0</difficult>
		<bndbox>
			<xmin>1865.0</xmin>
			<ymin>2312.0</ymin>
			<xmax>1914.0</xmax>
			<ymax>2351.0</ymax>
		</bndbox>
	</object>
	<object>
		<name>WF</name>
		<pose>Unspecified</pose>
		<truncated>0</truncated>
		<difficult>0</difficult>
		<bndbox>
			<xmin>1852.0</xmin>
			<ymin>2396.0</ymin>
			<xmax>1888.0</xmax>
			<ymax>2440.0</ymax>
		</bndbox>
	</object>
	<object>
		<name>WF</name>
		<pose>Unspecified</pose>
		<truncated>0</truncated>
		<difficult>0</difficult>
		<bndbox>
			<xmin>3308.0</xmin>
			<ymin>2805.0</ymin>
			<xmax>3383.0</xmax>
			<ymax>2855.0</ymax>
		</bndbox>
	</object>
	<object>
		<name>WF</name>
		<pose>Unspecified</pose>
		<truncated>0</truncated>
		<difficult>0</difficult>
		<bndbox>
			<xmin>2997.0</xmin>
			<ymin>2537.0</ymin>
			<xmax>3053.0</xmax>
			<ymax>2580.0</ymax>
		</bndbox>
	</object>
	<object>
		<name>WF</name>
		<pose>Unspecified</pose>
		<truncated>0</truncated>
		<difficult>0</difficult>
		<bndbox>
			<xmin>2961.0</xmin>
			<ymin>2447.0</ymin>
			<xmax>3026.0</xmax>
			<ymax>2494.0</ymax>
		</bndbox>
	</object>
	<object>
		<name>WF</name>
		<pose>Unspecified</pose>
		<truncated>0</truncated>
		<difficult>0</difficult>
		<bndbox>
			<xmin>2749.0</xmin>
			<ymin>2404.0</ymin>
			<xmax>2806.0</xmax>
			<ymax>2454.0</ymax>
		</bndbox>
	</object>
	<object>
		<name>WF</name>
		<pose>Unspecified</pose>
		<truncated>0</truncated>
		<difficult>0</difficult>
		<bndbox>
			<xmin>2675.0</xmin>
			<ymin>2378.0</ymin>
			<xmax>2734.0</xmax>
			<ymax>2425.0</ymax>
		</bndbox>
	</object>
	<object>
		<name>WF</name>
		<pose>Unspecified</pose>
		<truncated>0</truncated>
		<difficult>0</difficult>
		<bndbox>
			<xmin>2434.0</xmin>
			<ymin>2345.0</ymin>
			<xmax>2495.0</xmax>
			<ymax>2392.0</ymax>
		</bndbox>
	</object>
	<object>
		<name>WF</name>
		<pose>Unspecified</pose>
		<truncated>0</truncated>
		<difficult>0</difficult>
		<bndbox>
			<xmin>2345.0</xmin>
			<ymin>2472.0</ymin>
			<xmax>2398.0</xmax>
			<ymax>2509.0</ymax>
		</bndbox>
	</object>
	<object>
		<name>WF</name>
		<pose>Unspecified</pose>
		<truncated>0</truncated>
		<difficult>0</difficult>
		<bndbox>
			<xmin>2876.0</xmin>
			<ymin>2576.0</ymin>
			<xmax>2927.0</xmax>
			<ymax>2621.0</ymax>
		</bndbox>
	</object>
	<object>
		<name>WF</name>
		<pose>Unspecified</pose>
		<truncated>0</truncated>
		<difficult>0</difficult>
		<bndbox>
			<xmin>2312.0</xmin>
			<ymin>2583.0</ymin>
			<xmax>2363.0</xmax>
			<ymax>2618.0</ymax>
		</bndbox>
	</object>
	<object>
		<name>WF</name>
		<pose>Unspecified</pose>
		<truncated>0</truncated>
		<difficult>0</difficult>
		<bndbox>
			<xmin>2028.0</xmin>
			<ymin>2369.0</ymin>
			<xmax>2078.0</xmax>
			<ymax>2414.0</ymax>
		</bndbox>
	</object>
	<object>
		<name>WF</name>
		<pose>Unspecified</pose>
		<truncated>0</truncated>
		<difficult>0</difficult>
		<bndbox>
			<xmin>1920.0</xmin>
			<ymin>2265.0</ymin>
			<xmax>1960.0</xmax>
			<ymax>2312.0</ymax>
		</bndbox>
	</object>
	<object>
		<name>WF</name>
		<pose>Unspecified</pose>
		<truncated>0</truncated>
		<difficult>0</difficult>
		<bndbox>
			<xmin>1928.0</xmin>
			<ymin>2416.0</ymin>
			<xmax>1972.0</xmax>
			<ymax>2461.0</ymax>
		</bndbox>
	</object>
	<object>
		<name>WF</name>
		<pose>Unspecified</pose>
		<truncated>0</truncated>
		<difficult>0</difficult>
		<bndbox>
			<xmin>1800.0</xmin>
			<ymin>2586.0</ymin>
			<xmax>1849.0</xmax>
			<ymax>2625.0</ymax>
		</bndbox>
	</object>
	<object>
		<name>WF</name>
		<pose>Unspecified</pose>
		<truncated>0</truncated>
		<difficult>0</difficult>
		<bndbox>
			<xmin>1939.0</xmin>
			<ymin>2647.0</ymin>
			<xmax>2013.0</xmax>
			<ymax>2705.0</ymax>
		</bndbox>
	</object>
	<object>
		<name>WF</name>
		<pose>Unspecified</pose>
		<truncated>0</truncated>
		<difficult>0</difficult>
		<bndbox>
			<xmin>1824.0</xmin>
			<ymin>2776.0</ymin>
			<xmax>1866.0</xmax>
			<ymax>2828.0</ymax>
		</bndbox>
	</object>
	<object>
		<name>WF</name>
		<pose>Unspecified</pose>
		<truncated>0</truncated>
		<difficult>0</difficult>
		<bndbox>
			<xmin>2323.0</xmin>
			<ymin>2747.0</ymin>
			<xmax>2377.0</xmax>
			<ymax>2784.0</ymax>
		</bndbox>
	</object>
	<object>
		<name>WF</name>
		<pose>Unspecified</pose>
		<truncated>0</truncated>
		<difficult>0</difficult>
		<bndbox>
			<xmin>2761.0</xmin>
			<ymin>2717.0</ymin>
			<xmax>2805.0</xmax>
			<ymax>2760.0</ymax>
		</bndbox>
	</object>
	<object>
		<name>WF</name>
		<pose>Unspecified</pose>
		<truncated>0</truncated>
		<difficult>0</difficult>
		<bndbox>
			<xmin>2111.0</xmin>
			<ymin>2805.0</ymin>
			<xmax>2152.0</xmax>
			<ymax>2844.0</ymax>
		</bndbox>
	</object>
	<object>
		<name>WF</name>
		<pose>Unspecified</pose>
		<truncated>0</truncated>
		<difficult>0</difficult>
		<bndbox>
			<xmin>2089.0</xmin>
			<ymin>2844.0</ymin>
			<xmax>2120.0</xmax>
			<ymax>2875.0</ymax>
		</bndbox>
	</object>
	<object>
		<name>WF</name>
		<pose>Unspecified</pose>
		<truncated>0</truncated>
		<difficult>0</difficult>
		<bndbox>
			<xmin>2800.0</xmin>
			<ymin>2887.0</ymin>
			<xmax>2866.0</xmax>
			<ymax>2945.0</ymax>
		</bndbox>
	</object>
	<object>
		<name>WF</name>
		<pose>Unspecified</pose>
		<truncated>0</truncated>
		<difficult>0</difficult>
		<bndbox>
			<xmin>2459.0</xmin>
			<ymin>2717.0</ymin>
			<xmax>2510.0</xmax>
			<ymax>2762.0</ymax>
		</bndbox>
	</object>
	<object>
		<name>WF</name>
		<pose>Unspecified</pose>
		<truncated>0</truncated>
		<difficult>0</difficult>
		<bndbox>
			<xmin>1928.0</xmin>
			<ymin>2102.0</ymin>
			<xmax>1965.0</xmax>
			<ymax>2145.0</ymax>
		</bndbox>
	</object>
	<object>
		<name>WF</name>
		<pose>Unspecified</pose>
		<truncated>0</truncated>
		<difficult>0</difficult>
		<bndbox>
			<xmin>2084.0</xmin>
			<ymin>2197.0</ymin>
			<xmax>2145.0</xmax>
			<ymax>2249.0</ymax>
		</bndbox>
	</object>
	<object>
		<name>WF</name>
		<pose>Unspecified</pose>
		<truncated>0</truncated>
		<difficult>0</difficult>
		<bndbox>
			<xmin>1999.0</xmin>
			<ymin>2000.0</ymin>
			<xmax>2053.0</xmax>
			<ymax>2045.0</ymax>
		</bndbox>
	</object>
	<object>
		<name>WF</name>
		<pose>Unspecified</pose>
		<truncated>0</truncated>
		<difficult>0</difficult>
		<bndbox>
			<xmin>2234.0</xmin>
			<ymin>2857.0</ymin>
			<xmax>2296.0</xmax>
			<ymax>2904.0</ymax>
		</bndbox>
	</object>
	<object>
		<name>WF</name>
		<pose>Unspecified</pose>
		<truncated>0</truncated>
		<difficult>0</difficult>
		<bndbox>
			<xmin>2847.0</xmin>
			<ymin>2347.0</ymin>
			<xmax>2891.0</xmax>
			<ymax>2393.0</ymax>
		</bndbox>
	</object>
	<object>
		<name>WF</name>
		<pose>Unspecified</pose>
		<truncated>0</truncated>
		<difficult>0</difficult>
		<bndbox>
			<xmin>1591.0</xmin>
			<ymin>1989.0</ymin>
			<xmax>1641.0</xmax>
			<ymax>2038.0</ymax>
		</bndbox>
	</object>
	<object>
		<name>WF</name>
		<pose>Unspecified</pose>
		<truncated>0</truncated>
		<difficult>0</difficult>
		<bndbox>
			<xmin>1459.0</xmin>
			<ymin>1998.0</ymin>
			<xmax>1525.0</xmax>
			<ymax>2054.0</ymax>
		</bndbox>
	</object>
	<object>
		<name>WF</name>
		<pose>Unspecified</pose>
		<truncated>0</truncated>
		<difficult>0</difficult>
		<bndbox>
			<xmin>1260.0</xmin>
			<ymin>1914.0</ymin>
			<xmax>1319.0</xmax>
			<ymax>1971.0</ymax>
		</bndbox>
	</object>
	<object>
		<name>WF</name>
		<pose>Unspecified</pose>
		<truncated>0</truncated>
		<difficult>0</difficult>
		<bndbox>
			<xmin>1033.0</xmin>
			<ymin>1828.0</ymin>
			<xmax>1094.0</xmax>
			<ymax>1877.0</ymax>
		</bndbox>
	</object>
	<object>
		<name>WF</name>
		<pose>Unspecified</pose>
		<truncated>0</truncated>
		<difficult>0</difficult>
		<bndbox>
			<xmin>890.0</xmin>
			<ymin>1734.0</ymin>
			<xmax>939.0</xmax>
			<ymax>1779.0</ymax>
		</bndbox>
	</object>
	<object>
		<name>WF</name>
		<pose>Unspecified</pose>
		<truncated>0</truncated>
		<difficult>0</difficult>
		<bndbox>
			<xmin>793.0</xmin>
			<ymin>1730.0</ymin>
			<xmax>844.0</xmax>
			<ymax>1769.0</ymax>
		</bndbox>
	</object>
	<object>
		<name>WF</name>
		<pose>Unspecified</pose>
		<truncated>0</truncated>
		<difficult>0</difficult>
		<bndbox>
			<xmin>497.0</xmin>
			<ymin>1905.0</ymin>
			<xmax>558.0</xmax>
			<ymax>1946.0</ymax>
		</bndbox>
	</object>
	<object>
		<name>WF</name>
		<pose>Unspecified</pose>
		<truncated>0</truncated>
		<difficult>0</difficult>
		<bndbox>
			<xmin>460.0</xmin>
			<ymin>1856.0</ymin>
			<xmax>516.0</xmax>
			<ymax>1906.0</ymax>
		</bndbox>
	</object>
	<object>
		<name>WF</name>
		<pose>Unspecified</pose>
		<truncated>0</truncated>
		<difficult>0</difficult>
		<bndbox>
			<xmin>999.0</xmin>
			<ymin>2045.0</ymin>
			<xmax>1052.0</xmax>
			<ymax>2086.0</ymax>
		</bndbox>
	</object>
	<object>
		<name>WF</name>
		<pose>Unspecified</pose>
		<truncated>0</truncated>
		<difficult>0</difficult>
		<bndbox>
			<xmin>323.0</xmin>
			<ymin>2225.0</ymin>
			<xmax>380.0</xmax>
			<ymax>2276.0</ymax>
		</bndbox>
	</object>
	<object>
		<name>WF</name>
		<pose>Unspecified</pose>
		<truncated>0</truncated>
		<difficult>0</difficult>
		<bndbox>
			<xmin>55.0</xmin>
			<ymin>2156.0</ymin>
			<xmax>115.0</xmax>
			<ymax>2199.0</ymax>
		</bndbox>
	</object>
	<object>
		<name>WF</name>
		<pose>Unspecified</pose>
		<truncated>0</truncated>
		<difficult>0</difficult>
		<bndbox>
			<xmin>1154.0</xmin>
			<ymin>2426.0</ymin>
			<xmax>1201.0</xmax>
			<ymax>2460.0</ymax>
		</bndbox>
	</object>
	<object>
		<name>WF</name>
		<pose>Unspecified</pose>
		<truncated>0</truncated>
		<difficult>0</difficult>
		<bndbox>
			<xmin>1410.0</xmin>
			<ymin>2522.0</ymin>
			<xmax>1453.0</xmax>
			<ymax>2570.0</ymax>
		</bndbox>
	</object>
	<object>
		<name>WF</name>
		<pose>Unspecified</pose>
		<truncated>0</truncated>
		<difficult>0</difficult>
		<bndbox>
			<xmin>1446.0</xmin>
			<ymin>2644.0</ymin>
			<xmax>1500.0</xmax>
			<ymax>2693.0</ymax>
		</bndbox>
	</object>
	<object>
		<name>WF</name>
		<pose>Unspecified</pose>
		<truncated>0</truncated>
		<difficult>0</difficult>
		<bndbox>
			<xmin>1584.0</xmin>
			<ymin>2669.0</ymin>
			<xmax>1641.0</xmax>
			<ymax>2713.0</ymax>
		</bndbox>
	</object>
	<object>
		<name>WF</name>
		<pose>Unspecified</pose>
		<truncated>0</truncated>
		<difficult>0</difficult>
		<bndbox>
			<xmin>1038.0</xmin>
			<ymin>2568.0</ymin>
			<xmax>1093.0</xmax>
			<ymax>2619.0</ymax>
		</bndbox>
	</object>
	<object>
		<name>WF</name>
		<pose>Unspecified</pose>
		<truncated>0</truncated>
		<difficult>0</difficult>
		<bndbox>
			<xmin>752.0</xmin>
			<ymin>2175.0</ymin>
			<xmax>796.0</xmax>
			<ymax>2220.0</ymax>
		</bndbox>
	</object>
	<object>
		<name>WF</name>
		<pose>Unspecified</pose>
		<truncated>0</truncated>
		<difficult>0</difficult>
		<bndbox>
			<xmin>686.0</xmin>
			<ymin>2223.0</ymin>
			<xmax>736.0</xmax>
			<ymax>2270.0</ymax>
		</bndbox>
	</object>
	<object>
		<name>WF</name>
		<pose>Unspecified</pose>
		<truncated>0</truncated>
		<difficult>0</difficult>
		<bndbox>
			<xmin>99.0</xmin>
			<ymin>2303.0</ymin>
			<xmax>147.0</xmax>
			<ymax>2356.0</ymax>
		</bndbox>
	</object>
	<object>
		<name>WF</name>
		<pose>Unspecified</pose>
		<truncated>0</truncated>
		<difficult>0</difficult>
		<bndbox>
			<xmin>169.0</xmin>
			<ymin>2447.0</ymin>
			<xmax>226.0</xmax>
			<ymax>2492.0</ymax>
		</bndbox>
	</object>
	<object>
		<name>WF</name>
		<pose>Unspecified</pose>
		<truncated>0</truncated>
		<difficult>0</difficult>
		<bndbox>
			<xmin>63.0</xmin>
			<ymin>2510.0</ymin>
			<xmax>129.0</xmax>
			<ymax>2558.0</ymax>
		</bndbox>
	</object>
	<object>
		<name>WF</name>
		<pose>Unspecified</pose>
		<truncated>0</truncated>
		<difficult>0</difficult>
		<bndbox>
			<xmin>199.0</xmin>
			<ymin>2537.0</ymin>
			<xmax>252.0</xmax>
			<ymax>2579.0</ymax>
		</bndbox>
	</object>
	<object>
		<name>WF</name>
		<pose>Unspecified</pose>
		<truncated>0</truncated>
		<difficult>0</difficult>
		<bndbox>
			<xmin>194.0</xmin>
			<ymin>2610.0</ymin>
			<xmax>255.0</xmax>
			<ymax>2644.0</ymax>
		</bndbox>
	</object>
	<object>
		<name>WF</name>
		<pose>Unspecified</pose>
		<truncated>0</truncated>
		<difficult>0</difficult>
		<bndbox>
			<xmin>225.0</xmin>
			<ymin>2658.0</ymin>
			<xmax>266.0</xmax>
			<ymax>2694.0</ymax>
		</bndbox>
	</object>
	<object>
		<name>WF</name>
		<pose>Unspecified</pose>
		<truncated>0</truncated>
		<difficult>0</difficult>
		<bndbox>
			<xmin>183.0</xmin>
			<ymin>2814.0</ymin>
			<xmax>233.0</xmax>
			<ymax>2883.0</ymax>
		</bndbox>
	</object>
	<object>
		<name>WF</name>
		<pose>Unspecified</pose>
		<truncated>0</truncated>
		<difficult>0</difficult>
		<bndbox>
			<xmin>555.0</xmin>
			<ymin>2531.0</ymin>
			<xmax>610.0</xmax>
			<ymax>2578.0</ymax>
		</bndbox>
	</object>
	<object>
		<name>WF</name>
		<pose>Unspecified</pose>
		<truncated>0</truncated>
		<difficult>0</difficult>
		<bndbox>
			<xmin>802.0</xmin>
			<ymin>2660.0</ymin>
			<xmax>836.0</xmax>
			<ymax>2705.0</ymax>
		</bndbox>
	</object>
	<object>
		<name>WF</name>
		<pose>Unspecified</pose>
		<truncated>0</truncated>
		<difficult>0</difficult>
		<bndbox>
			<xmin>794.0</xmin>
			<ymin>2705.0</ymin>
			<xmax>838.0</xmax>
			<ymax>2747.0</ymax>
		</bndbox>
	</object>
	<object>
		<name>WF</name>
		<pose>Unspecified</pose>
		<truncated>0</truncated>
		<difficult>0</difficult>
		<bndbox>
			<xmin>663.0</xmin>
			<ymin>2629.0</ymin>
			<xmax>714.0</xmax>
			<ymax>2672.0</ymax>
		</bndbox>
	</object>
	<object>
		<name>WF</name>
		<pose>Unspecified</pose>
		<truncated>0</truncated>
		<difficult>0</difficult>
		<bndbox>
			<xmin>783.0</xmin>
			<ymin>2791.0</ymin>
			<xmax>848.0</xmax>
			<ymax>2834.0</ymax>
		</bndbox>
	</object>
	<object>
		<name>WF</name>
		<pose>Unspecified</pose>
		<truncated>0</truncated>
		<difficult>0</difficult>
		<bndbox>
			<xmin>664.0</xmin>
			<ymin>2823.0</ymin>
			<xmax>714.0</xmax>
			<ymax>2862.0</ymax>
		</bndbox>
	</object>
	<object>
		<name>WF</name>
		<pose>Unspecified</pose>
		<truncated>0</truncated>
		<difficult>0</difficult>
		<bndbox>
			<xmin>405.0</xmin>
			<ymin>2839.0</ymin>
			<xmax>449.0</xmax>
			<ymax>2875.0</ymax>
		</bndbox>
	</object>
	<object>
		<name>WF</name>
		<pose>Unspecified</pose>
		<truncated>0</truncated>
		<difficult>0</difficult>
		<bndbox>
			<xmin>833.0</xmin>
			<ymin>2068.0</ymin>
			<xmax>880.0</xmax>
			<ymax>2114.0</ymax>
		</bndbox>
	</object>
	<object>
		<name>WF</name>
		<pose>Unspecified</pose>
		<truncated>0</truncated>
		<difficult>0</difficult>
		<bndbox>
			<xmin>802.0</xmin>
			<ymin>2104.0</ymin>
			<xmax>847.0</xmax>
			<ymax>2144.0</ymax>
		</bndbox>
	</object>
	<object>
		<name>WF</name>
		<pose>Unspecified</pose>
		<truncated>0</truncated>
		<difficult>0</difficult>
		<bndbox>
			<xmin>1108.0</xmin>
			<ymin>2387.0</ymin>
			<xmax>1156.0</xmax>
			<ymax>2437.0</ymax>
		</bndbox>
	</object>
	<object>
		<name>WF</name>
		<pose>Unspecified</pose>
		<truncated>0</truncated>
		<difficult>0</difficult>
		<bndbox>
			<xmin>692.0</xmin>
			<ymin>2853.0</ymin>
			<xmax>742.0</xmax>
			<ymax>2898.0</ymax>
		</bndbox>
	</object>
	<object>
		<name>WF</name>
		<pose>Unspecified</pose>
		<truncated>0</truncated>
		<difficult>0</difficult>
		<bndbox>
			<xmin>1345.0</xmin>
			<ymin>2520.0</ymin>
			<xmax>1402.0</xmax>
			<ymax>2564.0</ymax>
		</bndbox>
	</object>
	<object>
		<name>WF</name>
		<pose>Unspecified</pose>
		<truncated>0</truncated>
		<difficult>0</difficult>
		<bndbox>
			<xmin>347.0</xmin>
			<ymin>2856.0</ymin>
			<xmax>388.0</xmax>
			<ymax>2893.0</ymax>
		</bndbox>
	</object>
	<object>
		<name>WF</name>
		<pose>Unspecified</pose>
		<truncated>0</truncated>
		<difficult>0</difficult>
		<bndbox>
			<xmin>847.0</xmin>
			<ymin>2437.0</ymin>
			<xmax>914.0</xmax>
			<ymax>2487.0</ymax>
		</bndbox>
	</object>
	<object>
		<name>WF</name>
		<pose>Unspecified</pose>
		<truncated>0</truncated>
		<difficult>0</difficult>
		<bndbox>
			<xmin>401.0</xmin>
			<ymin>2265.0</ymin>
			<xmax>462.0</xmax>
			<ymax>2317.0</ymax>
		</bndbox>
	</object>
	<object>
		<name>WF</name>
		<pose>Unspecified</pose>
		<truncated>0</truncated>
		<difficult>0</difficult>
		<bndbox>
			<xmin>589.0</xmin>
			<ymin>2835.0</ymin>
			<xmax>638.0</xmax>
			<ymax>2883.0</ymax>
		</bndbox>
	</object>
	<object>
		<name>WF</name>
		<pose>Unspecified</pose>
		<truncated>0</truncated>
		<difficult>0</difficult>
		<bndbox>
			<xmin>1136.0</xmin>
			<ymin>2242.0</ymin>
			<xmax>1190.0</xmax>
			<ymax>2292.0</ymax>
		</bndbox>
	</object>
	<object>
		<name>WF</name>
		<pose>Unspecified</pose>
		<truncated>0</truncated>
		<difficult>0</difficult>
		<bndbox>
			<xmin>1022.0</xmin>
			<ymin>2514.0</ymin>
			<xmax>1074.0</xmax>
			<ymax>2555.0</ymax>
		</bndbox>
	</object>
	<object>
		<name>WF</name>
		<pose>Unspecified</pose>
		<truncated>0</truncated>
		<difficult>0</difficult>
		<bndbox>
			<xmin>1473.0</xmin>
			<ymin>2681.0</ymin>
			<xmax>1526.0</xmax>
			<ymax>2731.0</ymax>
		</bndbox>
	</object>
	<object>
		<name>WF</name>
		<pose>Unspecified</pose>
		<truncated>0</truncated>
		<difficult>0</difficult>
		<bndbox>
			<xmin>970.0</xmin>
			<ymin>2751.0</ymin>
			<xmax>1016.0</xmax>
			<ymax>2796.0</ymax>
		</bndbox>
	</object>
</annotation>