<?xml version="1.0" encoding="utf-8"?>
<annotation>
	<folder>--</folder>
	<filename>--</filename>
	<path>--</path>
	<source>
		<database>Unknown</database>
	</source>
	<size>
		<width>3456</width>
		<height>5184</height>
	</size>
	<segmented>3</segmented>
	<object>
		<name>WF</name>
		<pose>Unspecified</pose>
		<truncated>0</truncated>
		<difficult>0</difficult>
		<bndbox>
			<xmin>2450.0</xmin>
			<ymin>548.0</ymin>
			<xmax>2522.0</xmax>
			<ymax>618.0</ymax>
		</bndbox>
	</object>
	<object>
		<name>WF</name>
		<pose>Unspecified</pose>
		<truncated>0</truncated>
		<difficult>0</difficult>
		<bndbox>
			<xmin>2586.0</xmin>
			<ymin>677.0</ymin>
			<xmax>2639.0</xmax>
			<ymax>736.0</ymax>
		</bndbox>
	</object>
	<object>
		<name>WF</name>
		<pose>Unspecified</pose>
		<truncated>0</truncated>
		<difficult>0</difficult>
		<bndbox>
			<xmin>2189.0</xmin>
			<ymin>223.0</ymin>
			<xmax>2250.0</xmax>
			<ymax>287.0</ymax>
		</bndbox>
	</object>
	<object>
		<name>WF</name>
		<pose>Unspecified</pose>
		<truncated>0</truncated>
		<difficult>0</difficult>
		<bndbox>
			<xmin>2341.0</xmin>
			<ymin>968.0</ymin>
			<xmax>2407.0</xmax>
			<ymax>1034.0</ymax>
		</bndbox>
	</object>
	<object>
		<name>WF</name>
		<pose>Unspecified</pose>
		<truncated>0</truncated>
		<difficult>0</difficult>
		<bndbox>
			<xmin>2660.0</xmin>
			<ymin>1455.0</ymin>
			<xmax>2733.0</xmax>
			<ymax>1526.0</ymax>
		</bndbox>
	</object>
	<object>
		<name>WF</name>
		<pose>Unspecified</pose>
		<truncated>0</truncated>
		<difficult>0</difficult>
		<bndbox>
			<xmin>1729.0</xmin>
			<ymin>1450.0</ymin>
			<xmax>1805.0</xmax>
			<ymax>1548.0</ymax>
		</bndbox>
	</object>
	<object>
		<name>WF</name>
		<pose>Unspecified</pose>
		<truncated>0</truncated>
		<difficult>0</difficult>
		<bndbox>
			<xmin>2765.0</xmin>
			<ymin>2162.0</ymin>
			<xmax>2833.0</xmax>
			<ymax>2249.0</ymax>
		</bndbox>
	</object>
	<object>
		<name>WF</name>
		<pose>Unspecified</pose>
		<truncated>0</truncated>
		<difficult>0</difficult>
		<bndbox>
			<xmin>2591.0</xmin>
			<ymin>2088.0</ymin>
			<xmax>2679.0</xmax>
			<ymax>2209.0</ymax>
		</bndbox>
	</object>
	<object>
		<name>WF</name>
		<pose>Unspecified</pose>
		<truncated>0</truncated>
		<difficult>0</difficult>
		<bndbox>
			<xmin>2357.0</xmin>
			<ymin>2101.0</ymin>
			<xmax>2462.0</xmax>
			<ymax>2223.0</ymax>
		</bndbox>
	</object>
	<object>
		<name>WF</name>
		<pose>Unspecified</pose>
		<truncated>0</truncated>
		<difficult>0</difficult>
		<bndbox>
			<xmin>2913.0</xmin>
			<ymin>2112.0</ymin>
			<xmax>2933.0</xmax>
			<ymax>2202.0</ymax>
		</bndbox>
	</object>
	<object>
		<name>WF</name>
		<pose>Unspecified</pose>
		<truncated>0</truncated>
		<difficult>0</difficult>
		<bndbox>
			<xmin>1959.0</xmin>
			<ymin>2464.0</ymin>
			<xmax>2007.0</xmax>
			<ymax>2530.0</ymax>
		</bndbox>
	</object>
	<object>
		<name>WF</name>
		<pose>Unspecified</pose>
		<truncated>0</truncated>
		<difficult>0</difficult>
		<bndbox>
			<xmin>1709.0</xmin>
			<ymin>2722.0</ymin>
			<xmax>1773.0</xmax>
			<ymax>2844.0</ymax>
		</bndbox>
	</object>
	<object>
		<name>WF</name>
		<pose>Unspecified</pose>
		<truncated>0</truncated>
		<difficult>0</difficult>
		<bndbox>
			<xmin>2804.0</xmin>
			<ymin>3687.0</ymin>
			<xmax>2870.0</xmax>
			<ymax>3774.0</ymax>
		</bndbox>
	</object>
	<object>
		<name>WF</name>
		<pose>Unspecified</pose>
		<truncated>0</truncated>
		<difficult>0</difficult>
		<bndbox>
			<xmin>1994.0</xmin>
			<ymin>3622.0</ymin>
			<xmax>2084.0</xmax>
			<ymax>3708.0</ymax>
		</bndbox>
	</object>
	<object>
		<name>WF</name>
		<pose>Unspecified</pose>
		<truncated>0</truncated>
		<difficult>0</difficult>
		<bndbox>
			<xmin>2091.0</xmin>
			<ymin>3930.0</ymin>
			<xmax>2144.0</xmax>
			<ymax>4013.0</ymax>
		</bndbox>
	</object>
	<object>
		<name>WF</name>
		<pose>Unspecified</pose>
		<truncated>0</truncated>
		<difficult>0</difficult>
		<bndbox>
			<xmin>2545.0</xmin>
			<ymin>4546.0</ymin>
			<xmax>2628.0</xmax>
			<ymax>4614.0</ymax>
		</bndbox>
	</object>
	<object>
		<name>WF</name>
		<pose>Unspecified</pose>
		<truncated>0</truncated>
		<difficult>0</difficult>
		<bndbox>
			<xmin>2486.0</xmin>
			<ymin>4853.0</ymin>
			<xmax>2573.0</xmax>
			<ymax>4950.0</ymax>
		</bndbox>
	</object>
	<object>
		<name>WF</name>
		<pose>Unspecified</pose>
		<truncated>0</truncated>
		<difficult>0</difficult>
		<bndbox>
			<xmin>2827.0</xmin>
			<ymin>4685.0</ymin>
			<xmax>2888.0</xmax>
			<ymax>4750.0</ymax>
		</bndbox>
	</object>
	<object>
		<name>WF</name>
		<pose>Unspecified</pose>
		<truncated>0</truncated>
		<difficult>0</difficult>
		<bndbox>
			<xmin>1909.0</xmin>
			<ymin>4922.0</ymin>
			<xmax>1956.0</xmax>
			<ymax>4980.0</ymax>
		</bndbox>
	</object>
	<object>
		<name>WF</name>
		<pose>Unspecified</pose>
		<truncated>0</truncated>
		<difficult>0</difficult>
		<bndbox>
			<xmin>1747.0</xmin>
			<ymin>4446.0</ymin>
			<xmax>1796.0</xmax>
			<ymax>4514.0</ymax>
		</bndbox>
	</object>
	<object>
		<name>WF</name>
		<pose>Unspecified</pose>
		<truncated>0</truncated>
		<difficult>0</difficult>
		<bndbox>
			<xmin>1154.0</xmin>
			<ymin>373.0</ymin>
			<xmax>1225.0</xmax>
			<ymax>484.0</ymax>
		</bndbox>
	</object>
	<object>
		<name>WF</name>
		<pose>Unspecified</pose>
		<truncated>0</truncated>
		<difficult>0</difficult>
		<bndbox>
			<xmin>1086.0</xmin>
			<ymin>397.0</ymin>
			<xmax>1141.0</xmax>
			<ymax>508.0</ymax>
		</bndbox>
	</object>
	<object>
		<name>WF</name>
		<pose>Unspecified</pose>
		<truncated>0</truncated>
		<difficult>0</difficult>
		<bndbox>
			<xmin>713.0</xmin>
			<ymin>310.0</ymin>
			<xmax>786.0</xmax>
			<ymax>424.0</ymax>
		</bndbox>
	</object>
	<object>
		<name>WF</name>
		<pose>Unspecified</pose>
		<truncated>0</truncated>
		<difficult>0</difficult>
		<bndbox>
			<xmin>547.0</xmin>
			<ymin>919.0</ymin>
			<xmax>631.0</xmax>
			<ymax>1045.0</ymax>
		</bndbox>
	</object>
	<object>
		<name>WF</name>
		<pose>Unspecified</pose>
		<truncated>0</truncated>
		<difficult>0</difficult>
		<bndbox>
			<xmin>1179.0</xmin>
			<ymin>890.0</ymin>
			<xmax>1263.0</xmax>
			<ymax>1037.0</ymax>
		</bndbox>
	</object>
	<object>
		<name>WF</name>
		<pose>Unspecified</pose>
		<truncated>0</truncated>
		<difficult>0</difficult>
		<bndbox>
			<xmin>1065.0</xmin>
			<ymin>1347.0</ymin>
			<xmax>1175.0</xmax>
			<ymax>1466.0</ymax>
		</bndbox>
	</object>
	<object>
		<name>WF</name>
		<pose>Unspecified</pose>
		<truncated>0</truncated>
		<difficult>0</difficult>
		<bndbox>
			<xmin>1534.0</xmin>
			<ymin>802.0</ymin>
			<xmax>1610.0</xmax>
			<ymax>903.0</ymax>
		</bndbox>
	</object>
	<object>
		<name>WF</name>
		<pose>Unspecified</pose>
		<truncated>0</truncated>
		<difficult>0</difficult>
		<bndbox>
			<xmin>1486.0</xmin>
			<ymin>1912.0</ymin>
			<xmax>1560.0</xmax>
			<ymax>2006.0</ymax>
		</bndbox>
	</object>
	<object>
		<name>WF</name>
		<pose>Unspecified</pose>
		<truncated>0</truncated>
		<difficult>0</difficult>
		<bndbox>
			<xmin>975.0</xmin>
			<ymin>1947.0</ymin>
			<xmax>1037.0</xmax>
			<ymax>1994.0</ymax>
		</bndbox>
	</object>
	<object>
		<name>WF</name>
		<pose>Unspecified</pose>
		<truncated>0</truncated>
		<difficult>0</difficult>
		<bndbox>
			<xmin>802.0</xmin>
			<ymin>2101.0</ymin>
			<xmax>866.0</xmax>
			<ymax>2175.0</ymax>
		</bndbox>
	</object>
	<object>
		<name>WF</name>
		<pose>Unspecified</pose>
		<truncated>0</truncated>
		<difficult>0</difficult>
		<bndbox>
			<xmin>573.0</xmin>
			<ymin>2202.0</ymin>
			<xmax>633.0</xmax>
			<ymax>2289.0</ymax>
		</bndbox>
	</object>
	<object>
		<name>WF</name>
		<pose>Unspecified</pose>
		<truncated>0</truncated>
		<difficult>0</difficult>
		<bndbox>
			<xmin>852.0</xmin>
			<ymin>2693.0</ymin>
			<xmax>926.0</xmax>
			<ymax>2775.0</ymax>
		</bndbox>
	</object>
	<object>
		<name>WF</name>
		<pose>Unspecified</pose>
		<truncated>0</truncated>
		<difficult>0</difficult>
		<bndbox>
			<xmin>1049.0</xmin>
			<ymin>2793.0</ymin>
			<xmax>1112.0</xmax>
			<ymax>2888.0</ymax>
		</bndbox>
	</object>
	<object>
		<name>WF</name>
		<pose>Unspecified</pose>
		<truncated>0</truncated>
		<difficult>0</difficult>
		<bndbox>
			<xmin>1634.0</xmin>
			<ymin>1836.0</ymin>
			<xmax>1670.0</xmax>
			<ymax>1910.0</ymax>
		</bndbox>
	</object>
</annotation>