<?xml version="1.0" encoding="utf-8"?>
<annotation>
	<folder>--</folder>
	<filename>--</filename>
	<path>--</path>
	<source>
		<database>Unknown</database>
	</source>
	<size>
		<width>3456</width>
		<height>5184</height>
	</size>
	<segmented>3</segmented>
	<object>
		<name>WF</name>
		<pose>Unspecified</pose>
		<truncated>0</truncated>
		<difficult>0</difficult>
		<bndbox>
			<xmin>1525.0</xmin>
			<ymin>4426.0</ymin>
			<xmax>1598.0</xmax>
			<ymax>4491.0</ymax>
		</bndbox>
	</object>
	<object>
		<name>WF</name>
		<pose>Unspecified</pose>
		<truncated>0</truncated>
		<difficult>0</difficult>
		<bndbox>
			<xmin>1485.0</xmin>
			<ymin>4578.0</ymin>
			<xmax>1548.0</xmax>
			<ymax>4633.0</ymax>
		</bndbox>
	</object>
	<object>
		<name>WF</name>
		<pose>Unspecified</pose>
		<truncated>0</truncated>
		<difficult>0</difficult>
		<bndbox>
			<xmin>1603.0</xmin>
			<ymin>3901.0</ymin>
			<xmax>1664.0</xmax>
			<ymax>3981.0</ymax>
		</bndbox>
	</object>
	<object>
		<name>WF</name>
		<pose>Unspecified</pose>
		<truncated>0</truncated>
		<difficult>0</difficult>
		<bndbox>
			<xmin>1077.0</xmin>
			<ymin>3522.0</ymin>
			<xmax>1137.0</xmax>
			<ymax>3584.0</ymax>
		</bndbox>
	</object>
	<object>
		<name>WF</name>
		<pose>Unspecified</pose>
		<truncated>0</truncated>
		<difficult>0</difficult>
		<bndbox>
			<xmin>840.0</xmin>
			<ymin>3612.0</ymin>
			<xmax>884.0</xmax>
			<ymax>3688.0</ymax>
		</bndbox>
	</object>
	<object>
		<name>WF</name>
		<pose>Unspecified</pose>
		<truncated>0</truncated>
		<difficult>0</difficult>
		<bndbox>
			<xmin>663.0</xmin>
			<ymin>3997.0</ymin>
			<xmax>724.0</xmax>
			<ymax>4059.0</ymax>
		</bndbox>
	</object>
	<object>
		<name>WF</name>
		<pose>Unspecified</pose>
		<truncated>0</truncated>
		<difficult>0</difficult>
		<bndbox>
			<xmin>945.0</xmin>
			<ymin>3610.0</ymin>
			<xmax>1003.0</xmax>
			<ymax>3682.0</ymax>
		</bndbox>
	</object>
	<object>
		<name>WF</name>
		<pose>Unspecified</pose>
		<truncated>0</truncated>
		<difficult>0</difficult>
		<bndbox>
			<xmin>768.0</xmin>
			<ymin>4776.0</ymin>
			<xmax>811.0</xmax>
			<ymax>4836.0</ymax>
		</bndbox>
	</object>
	<object>
		<name>WF</name>
		<pose>Unspecified</pose>
		<truncated>0</truncated>
		<difficult>0</difficult>
		<bndbox>
			<xmin>913.0</xmin>
			<ymin>4496.0</ymin>
			<xmax>969.0</xmax>
			<ymax>4562.0</ymax>
		</bndbox>
	</object>
	<object>
		<name>WF</name>
		<pose>Unspecified</pose>
		<truncated>0</truncated>
		<difficult>0</difficult>
		<bndbox>
			<xmin>1572.0</xmin>
			<ymin>4657.0</ymin>
			<xmax>1633.0</xmax>
			<ymax>4717.0</ymax>
		</bndbox>
	</object>
	<object>
		<name>WF</name>
		<pose>Unspecified</pose>
		<truncated>0</truncated>
		<difficult>0</difficult>
		<bndbox>
			<xmin>630.0</xmin>
			<ymin>2627.0</ymin>
			<xmax>700.0</xmax>
			<ymax>2700.0</ymax>
		</bndbox>
	</object>
	<object>
		<name>WF</name>
		<pose>Unspecified</pose>
		<truncated>0</truncated>
		<difficult>0</difficult>
		<bndbox>
			<xmin>564.0</xmin>
			<ymin>2979.0</ymin>
			<xmax>627.0</xmax>
			<ymax>3047.0</ymax>
		</bndbox>
	</object>
	<object>
		<name>WF</name>
		<pose>Unspecified</pose>
		<truncated>0</truncated>
		<difficult>0</difficult>
		<bndbox>
			<xmin>718.0</xmin>
			<ymin>1968.0</ymin>
			<xmax>782.0</xmax>
			<ymax>2032.0</ymax>
		</bndbox>
	</object>
	<object>
		<name>WF</name>
		<pose>Unspecified</pose>
		<truncated>0</truncated>
		<difficult>0</difficult>
		<bndbox>
			<xmin>935.0</xmin>
			<ymin>2079.0</ymin>
			<xmax>990.0</xmax>
			<ymax>2171.0</ymax>
		</bndbox>
	</object>
	<object>
		<name>WF</name>
		<pose>Unspecified</pose>
		<truncated>0</truncated>
		<difficult>0</difficult>
		<bndbox>
			<xmin>1018.0</xmin>
			<ymin>2406.0</ymin>
			<xmax>1083.0</xmax>
			<ymax>2475.0</ymax>
		</bndbox>
	</object>
	<object>
		<name>WF</name>
		<pose>Unspecified</pose>
		<truncated>0</truncated>
		<difficult>0</difficult>
		<bndbox>
			<xmin>1117.0</xmin>
			<ymin>2855.0</ymin>
			<xmax>1181.0</xmax>
			<ymax>2938.0</ymax>
		</bndbox>
	</object>
	<object>
		<name>WF</name>
		<pose>Unspecified</pose>
		<truncated>0</truncated>
		<difficult>0</difficult>
		<bndbox>
			<xmin>1436.0</xmin>
			<ymin>2312.0</ymin>
			<xmax>1505.0</xmax>
			<ymax>2379.0</ymax>
		</bndbox>
	</object>
	<object>
		<name>WF</name>
		<pose>Unspecified</pose>
		<truncated>0</truncated>
		<difficult>0</difficult>
		<bndbox>
			<xmin>1408.0</xmin>
			<ymin>1786.0</ymin>
			<xmax>1469.0</xmax>
			<ymax>1859.0</ymax>
		</bndbox>
	</object>
	<object>
		<name>WF</name>
		<pose>Unspecified</pose>
		<truncated>0</truncated>
		<difficult>0</difficult>
		<bndbox>
			<xmin>1620.0</xmin>
			<ymin>3363.0</ymin>
			<xmax>1676.0</xmax>
			<ymax>3420.0</ymax>
		</bndbox>
	</object>
	<object>
		<name>WF</name>
		<pose>Unspecified</pose>
		<truncated>0</truncated>
		<difficult>0</difficult>
		<bndbox>
			<xmin>1645.0</xmin>
			<ymin>2544.0</ymin>
			<xmax>1704.0</xmax>
			<ymax>2606.0</ymax>
		</bndbox>
	</object>
	<object>
		<name>WF</name>
		<pose>Unspecified</pose>
		<truncated>0</truncated>
		<difficult>0</difficult>
		<bndbox>
			<xmin>1729.0</xmin>
			<ymin>2926.0</ymin>
			<xmax>1775.0</xmax>
			<ymax>3006.0</ymax>
		</bndbox>
	</object>
	<object>
		<name>WF</name>
		<pose>Unspecified</pose>
		<truncated>0</truncated>
		<difficult>0</difficult>
		<bndbox>
			<xmin>1644.0</xmin>
			<ymin>2030.0</ymin>
			<xmax>1708.0</xmax>
			<ymax>2105.0</ymax>
		</bndbox>
	</object>
	<object>
		<name>WF</name>
		<pose>Unspecified</pose>
		<truncated>0</truncated>
		<difficult>0</difficult>
		<bndbox>
			<xmin>715.0</xmin>
			<ymin>2889.0</ymin>
			<xmax>768.0</xmax>
			<ymax>2942.0</ymax>
		</bndbox>
	</object>
	<object>
		<name>WF</name>
		<pose>Unspecified</pose>
		<truncated>0</truncated>
		<difficult>0</difficult>
		<bndbox>
			<xmin>1560.0</xmin>
			<ymin>1816.0</ymin>
			<xmax>1626.0</xmax>
			<ymax>1876.0</ymax>
		</bndbox>
	</object>
	<object>
		<name>WF</name>
		<pose>Unspecified</pose>
		<truncated>0</truncated>
		<difficult>0</difficult>
		<bndbox>
			<xmin>1608.0</xmin>
			<ymin>1726.0</ymin>
			<xmax>1673.0</xmax>
			<ymax>1777.0</ymax>
		</bndbox>
	</object>
	<object>
		<name>WF</name>
		<pose>Unspecified</pose>
		<truncated>0</truncated>
		<difficult>0</difficult>
		<bndbox>
			<xmin>569.0</xmin>
			<ymin>2141.0</ymin>
			<xmax>628.0</xmax>
			<ymax>2203.0</ymax>
		</bndbox>
	</object>
	<object>
		<name>WF</name>
		<pose>Unspecified</pose>
		<truncated>0</truncated>
		<difficult>0</difficult>
		<bndbox>
			<xmin>625.0</xmin>
			<ymin>700.0</ymin>
			<xmax>774.0</xmax>
			<ymax>834.0</ymax>
		</bndbox>
	</object>
	<object>
		<name>WF</name>
		<pose>Unspecified</pose>
		<truncated>0</truncated>
		<difficult>0</difficult>
		<bndbox>
			<xmin>598.0</xmin>
			<ymin>152.0</ymin>
			<xmax>661.0</xmax>
			<ymax>213.0</ymax>
		</bndbox>
	</object>
	<object>
		<name>WF</name>
		<pose>Unspecified</pose>
		<truncated>0</truncated>
		<difficult>0</difficult>
		<bndbox>
			<xmin>627.0</xmin>
			<ymin>22.0</ymin>
			<xmax>682.0</xmax>
			<ymax>91.0</ymax>
		</bndbox>
	</object>
	<object>
		<name>WF</name>
		<pose>Unspecified</pose>
		<truncated>0</truncated>
		<difficult>0</difficult>
		<bndbox>
			<xmin>803.0</xmin>
			<ymin>1116.0</ymin>
			<xmax>869.0</xmax>
			<ymax>1198.0</ymax>
		</bndbox>
	</object>
	<object>
		<name>WF</name>
		<pose>Unspecified</pose>
		<truncated>0</truncated>
		<difficult>0</difficult>
		<bndbox>
			<xmin>576.0</xmin>
			<ymin>1287.0</ymin>
			<xmax>637.0</xmax>
			<ymax>1354.0</ymax>
		</bndbox>
	</object>
	<object>
		<name>WF</name>
		<pose>Unspecified</pose>
		<truncated>0</truncated>
		<difficult>0</difficult>
		<bndbox>
			<xmin>672.0</xmin>
			<ymin>1383.0</ymin>
			<xmax>724.0</xmax>
			<ymax>1437.0</ymax>
		</bndbox>
	</object>
	<object>
		<name>WF</name>
		<pose>Unspecified</pose>
		<truncated>0</truncated>
		<difficult>0</difficult>
		<bndbox>
			<xmin>760.0</xmin>
			<ymin>1422.0</ymin>
			<xmax>803.0</xmax>
			<ymax>1487.0</ymax>
		</bndbox>
	</object>
	<object>
		<name>WF</name>
		<pose>Unspecified</pose>
		<truncated>0</truncated>
		<difficult>0</difficult>
		<bndbox>
			<xmin>935.0</xmin>
			<ymin>1416.0</ymin>
			<xmax>992.0</xmax>
			<ymax>1488.0</ymax>
		</bndbox>
	</object>
	<object>
		<name>WF</name>
		<pose>Unspecified</pose>
		<truncated>0</truncated>
		<difficult>0</difficult>
		<bndbox>
			<xmin>1385.0</xmin>
			<ymin>1559.0</ymin>
			<xmax>1451.0</xmax>
			<ymax>1624.0</ymax>
		</bndbox>
	</object>
	<object>
		<name>WF</name>
		<pose>Unspecified</pose>
		<truncated>0</truncated>
		<difficult>0</difficult>
		<bndbox>
			<xmin>1390.0</xmin>
			<ymin>1076.0</ymin>
			<xmax>1452.0</xmax>
			<ymax>1151.0</ymax>
		</bndbox>
	</object>
	<object>
		<name>WF</name>
		<pose>Unspecified</pose>
		<truncated>0</truncated>
		<difficult>0</difficult>
		<bndbox>
			<xmin>1526.0</xmin>
			<ymin>1458.0</ymin>
			<xmax>1604.0</xmax>
			<ymax>1529.0</ymax>
		</bndbox>
	</object>
	<object>
		<name>WF</name>
		<pose>Unspecified</pose>
		<truncated>0</truncated>
		<difficult>0</difficult>
		<bndbox>
			<xmin>1542.0</xmin>
			<ymin>874.0</ymin>
			<xmax>1606.0</xmax>
			<ymax>962.0</ymax>
		</bndbox>
	</object>
	<object>
		<name>WF</name>
		<pose>Unspecified</pose>
		<truncated>0</truncated>
		<difficult>0</difficult>
		<bndbox>
			<xmin>856.0</xmin>
			<ymin>237.0</ymin>
			<xmax>903.0</xmax>
			<ymax>298.0</ymax>
		</bndbox>
	</object>
	<object>
		<name>WF</name>
		<pose>Unspecified</pose>
		<truncated>0</truncated>
		<difficult>0</difficult>
		<bndbox>
			<xmin>1243.0</xmin>
			<ymin>106.0</ymin>
			<xmax>1300.0</xmax>
			<ymax>164.0</ymax>
		</bndbox>
	</object>
	<object>
		<name>WF</name>
		<pose>Unspecified</pose>
		<truncated>0</truncated>
		<difficult>0</difficult>
		<bndbox>
			<xmin>971.0</xmin>
			<ymin>29.0</ymin>
			<xmax>1027.0</xmax>
			<ymax>90.0</ymax>
		</bndbox>
	</object>
	<object>
		<name>WF</name>
		<pose>Unspecified</pose>
		<truncated>0</truncated>
		<difficult>0</difficult>
		<bndbox>
			<xmin>955.0</xmin>
			<ymin>340.0</ymin>
			<xmax>1028.0</xmax>
			<ymax>415.0</ymax>
		</bndbox>
	</object>
	<object>
		<name>WF</name>
		<pose>Unspecified</pose>
		<truncated>0</truncated>
		<difficult>0</difficult>
		<bndbox>
			<xmin>2062.0</xmin>
			<ymin>4634.0</ymin>
			<xmax>2126.0</xmax>
			<ymax>4709.0</ymax>
		</bndbox>
	</object>
	<object>
		<name>WF</name>
		<pose>Unspecified</pose>
		<truncated>0</truncated>
		<difficult>0</difficult>
		<bndbox>
			<xmin>1843.0</xmin>
			<ymin>4275.0</ymin>
			<xmax>1897.0</xmax>
			<ymax>4356.0</ymax>
		</bndbox>
	</object>
	<object>
		<name>WF</name>
		<pose>Unspecified</pose>
		<truncated>0</truncated>
		<difficult>0</difficult>
		<bndbox>
			<xmin>2261.0</xmin>
			<ymin>4738.0</ymin>
			<xmax>2312.0</xmax>
			<ymax>4802.0</ymax>
		</bndbox>
	</object>
	<object>
		<name>WF</name>
		<pose>Unspecified</pose>
		<truncated>0</truncated>
		<difficult>0</difficult>
		<bndbox>
			<xmin>2252.0</xmin>
			<ymin>4857.0</ymin>
			<xmax>2311.0</xmax>
			<ymax>4911.0</ymax>
		</bndbox>
	</object>
	<object>
		<name>WF</name>
		<pose>Unspecified</pose>
		<truncated>0</truncated>
		<difficult>0</difficult>
		<bndbox>
			<xmin>2293.0</xmin>
			<ymin>5104.0</ymin>
			<xmax>2364.0</xmax>
			<ymax>5168.0</ymax>
		</bndbox>
	</object>
	<object>
		<name>WF</name>
		<pose>Unspecified</pose>
		<truncated>0</truncated>
		<difficult>0</difficult>
		<bndbox>
			<xmin>2393.0</xmin>
			<ymin>4791.0</ymin>
			<xmax>2451.0</xmax>
			<ymax>4862.0</ymax>
		</bndbox>
	</object>
	<object>
		<name>WF</name>
		<pose>Unspecified</pose>
		<truncated>0</truncated>
		<difficult>0</difficult>
		<bndbox>
			<xmin>2717.0</xmin>
			<ymin>4804.0</ymin>
			<xmax>2761.0</xmax>
			<ymax>4862.0</ymax>
		</bndbox>
	</object>
	<object>
		<name>WF</name>
		<pose>Unspecified</pose>
		<truncated>0</truncated>
		<difficult>0</difficult>
		<bndbox>
			<xmin>2932.0</xmin>
			<ymin>4968.0</ymin>
			<xmax>2991.0</xmax>
			<ymax>5043.0</ymax>
		</bndbox>
	</object>
	<object>
		<name>WF</name>
		<pose>Unspecified</pose>
		<truncated>0</truncated>
		<difficult>0</difficult>
		<bndbox>
			<xmin>2557.0</xmin>
			<ymin>4028.0</ymin>
			<xmax>2634.0</xmax>
			<ymax>4121.0</ymax>
		</bndbox>
	</object>
	<object>
		<name>WF</name>
		<pose>Unspecified</pose>
		<truncated>0</truncated>
		<difficult>0</difficult>
		<bndbox>
			<xmin>2696.0</xmin>
			<ymin>3842.0</ymin>
			<xmax>2756.0</xmax>
			<ymax>3915.0</ymax>
		</bndbox>
	</object>
	<object>
		<name>WF</name>
		<pose>Unspecified</pose>
		<truncated>0</truncated>
		<difficult>0</difficult>
		<bndbox>
			<xmin>2955.0</xmin>
			<ymin>4424.0</ymin>
			<xmax>3014.0</xmax>
			<ymax>4500.0</ymax>
		</bndbox>
	</object>
	<object>
		<name>WF</name>
		<pose>Unspecified</pose>
		<truncated>0</truncated>
		<difficult>0</difficult>
		<bndbox>
			<xmin>2497.0</xmin>
			<ymin>4876.0</ymin>
			<xmax>2551.0</xmax>
			<ymax>4934.0</ymax>
		</bndbox>
	</object>
	<object>
		<name>WF</name>
		<pose>Unspecified</pose>
		<truncated>0</truncated>
		<difficult>0</difficult>
		<bndbox>
			<xmin>2962.0</xmin>
			<ymin>4131.0</ymin>
			<xmax>3027.0</xmax>
			<ymax>4201.0</ymax>
		</bndbox>
	</object>
	<object>
		<name>WF</name>
		<pose>Unspecified</pose>
		<truncated>0</truncated>
		<difficult>0</difficult>
		<bndbox>
			<xmin>2347.0</xmin>
			<ymin>2435.0</ymin>
			<xmax>2406.0</xmax>
			<ymax>2511.0</ymax>
		</bndbox>
	</object>
	<object>
		<name>WF</name>
		<pose>Unspecified</pose>
		<truncated>0</truncated>
		<difficult>0</difficult>
		<bndbox>
			<xmin>2462.0</xmin>
			<ymin>2419.0</ymin>
			<xmax>2538.0</xmax>
			<ymax>2481.0</ymax>
		</bndbox>
	</object>
	<object>
		<name>WF</name>
		<pose>Unspecified</pose>
		<truncated>0</truncated>
		<difficult>0</difficult>
		<bndbox>
			<xmin>2744.0</xmin>
			<ymin>2639.0</ymin>
			<xmax>2804.0</xmax>
			<ymax>2690.0</ymax>
		</bndbox>
	</object>
	<object>
		<name>WF</name>
		<pose>Unspecified</pose>
		<truncated>0</truncated>
		<difficult>0</difficult>
		<bndbox>
			<xmin>2379.0</xmin>
			<ymin>3408.0</ymin>
			<xmax>2443.0</xmax>
			<ymax>3453.0</ymax>
		</bndbox>
	</object>
	<object>
		<name>WF</name>
		<pose>Unspecified</pose>
		<truncated>0</truncated>
		<difficult>0</difficult>
		<bndbox>
			<xmin>2030.0</xmin>
			<ymin>1277.0</ymin>
			<xmax>2112.0</xmax>
			<ymax>1356.0</ymax>
		</bndbox>
	</object>
	<object>
		<name>WF</name>
		<pose>Unspecified</pose>
		<truncated>0</truncated>
		<difficult>0</difficult>
		<bndbox>
			<xmin>1944.0</xmin>
			<ymin>1517.0</ymin>
			<xmax>1999.0</xmax>
			<ymax>1580.0</ymax>
		</bndbox>
	</object>
	<object>
		<name>WF</name>
		<pose>Unspecified</pose>
		<truncated>0</truncated>
		<difficult>0</difficult>
		<bndbox>
			<xmin>2276.0</xmin>
			<ymin>1637.0</ymin>
			<xmax>2341.0</xmax>
			<ymax>1714.0</ymax>
		</bndbox>
	</object>
	<object>
		<name>WF</name>
		<pose>Unspecified</pose>
		<truncated>0</truncated>
		<difficult>0</difficult>
		<bndbox>
			<xmin>2403.0</xmin>
			<ymin>1337.0</ymin>
			<xmax>2472.0</xmax>
			<ymax>1420.0</ymax>
		</bndbox>
	</object>
	<object>
		<name>WF</name>
		<pose>Unspecified</pose>
		<truncated>0</truncated>
		<difficult>0</difficult>
		<bndbox>
			<xmin>2592.0</xmin>
			<ymin>1024.0</ymin>
			<xmax>2667.0</xmax>
			<ymax>1090.0</ymax>
		</bndbox>
	</object>
	<object>
		<name>WF</name>
		<pose>Unspecified</pose>
		<truncated>0</truncated>
		<difficult>0</difficult>
		<bndbox>
			<xmin>2675.0</xmin>
			<ymin>419.0</ymin>
			<xmax>2757.0</xmax>
			<ymax>499.0</ymax>
		</bndbox>
	</object>
	<object>
		<name>WF</name>
		<pose>Unspecified</pose>
		<truncated>0</truncated>
		<difficult>0</difficult>
		<bndbox>
			<xmin>1833.0</xmin>
			<ymin>141.0</ymin>
			<xmax>1901.0</xmax>
			<ymax>195.0</ymax>
		</bndbox>
	</object>
	<object>
		<name>WF</name>
		<pose>Unspecified</pose>
		<truncated>0</truncated>
		<difficult>0</difficult>
		<bndbox>
			<xmin>2025.0</xmin>
			<ymin>41.0</ymin>
			<xmax>2089.0</xmax>
			<ymax>85.0</ymax>
		</bndbox>
	</object>
	<object>
		<name>WF</name>
		<pose>Unspecified</pose>
		<truncated>0</truncated>
		<difficult>0</difficult>
		<bndbox>
			<xmin>2219.0</xmin>
			<ymin>232.0</ymin>
			<xmax>2311.0</xmax>
			<ymax>295.0</ymax>
		</bndbox>
	</object>
	<object>
		<name>WF</name>
		<pose>Unspecified</pose>
		<truncated>0</truncated>
		<difficult>0</difficult>
		<bndbox>
			<xmin>2325.0</xmin>
			<ymin>3.0</ymin>
			<xmax>2414.0</xmax>
			<ymax>77.0</ymax>
		</bndbox>
	</object>
	<object>
		<name>WF</name>
		<pose>Unspecified</pose>
		<truncated>0</truncated>
		<difficult>0</difficult>
		<bndbox>
			<xmin>2532.0</xmin>
			<ymin>625.0</ymin>
			<xmax>2602.0</xmax>
			<ymax>704.0</ymax>
		</bndbox>
	</object>
	<object>
		<name>WF</name>
		<pose>Unspecified</pose>
		<truncated>0</truncated>
		<difficult>0</difficult>
		<bndbox>
			<xmin>2543.0</xmin>
			<ymin>309.0</ymin>
			<xmax>2602.0</xmax>
			<ymax>391.0</ymax>
		</bndbox>
	</object>
</annotation>