<?xml version="1.0" encoding="utf-8"?>
<annotation>
	<folder>--</folder>
	<filename>--</filename>
	<path>--</path>
	<source>
		<database>Unknown</database>
	</source>
	<size>
		<width>3456</width>
		<height>5184</height>
	</size>
	<segmented>3</segmented>
	<object>
		<name>WF</name>
		<pose>Unspecified</pose>
		<truncated>0</truncated>
		<difficult>0</difficult>
		<bndbox>
			<xmin>3638</xmin>
			<ymin>1171</ymin>
			<xmax>3702</xmax>
			<ymax>1235</ymax>
		</bndbox>
	</object>
	<object>
		<name>WF</name>
		<pose>Unspecified</pose>
		<truncated>0</truncated>
		<difficult>0</difficult>
		<bndbox>
			<xmin>4191</xmin>
			<ymin>987</ymin>
			<xmax>4255</xmax>
			<ymax>1051</ymax>
		</bndbox>
	</object>
	<object>
		<name>WF</name>
		<pose>Unspecified</pose>
		<truncated>0</truncated>
		<difficult>0</difficult>
		<bndbox>
			<xmin>4574</xmin>
			<ymin>1168</ymin>
			<xmax>4638</xmax>
			<ymax>1232</ymax>
		</bndbox>
	</object>
	<object>
		<name>WF</name>
		<pose>Unspecified</pose>
		<truncated>0</truncated>
		<difficult>0</difficult>
		<bndbox>
			<xmin>4553</xmin>
			<ymin>1106</ymin>
			<xmax>4617</xmax>
			<ymax>1170</ymax>
		</bndbox>
	</object>
	<object>
		<name>WF</name>
		<pose>Unspecified</pose>
		<truncated>0</truncated>
		<difficult>0</difficult>
		<bndbox>
			<xmin>4401</xmin>
			<ymin>482</ymin>
			<xmax>4465</xmax>
			<ymax>546</ymax>
		</bndbox>
	</object>
	<object>
		<name>WF</name>
		<pose>Unspecified</pose>
		<truncated>0</truncated>
		<difficult>0</difficult>
		<bndbox>
			<xmin>4755</xmin>
			<ymin>491</ymin>
			<xmax>4819</xmax>
			<ymax>555</ymax>
		</bndbox>
	</object>
	<object>
		<name>WF</name>
		<pose>Unspecified</pose>
		<truncated>0</truncated>
		<difficult>0</difficult>
		<bndbox>
			<xmin>740</xmin>
			<ymin>2467</ymin>
			<xmax>804</xmax>
			<ymax>2531</ymax>
		</bndbox>
	</object>
	<object>
		<name>WF</name>
		<pose>Unspecified</pose>
		<truncated>0</truncated>
		<difficult>0</difficult>
		<bndbox>
			<xmin>1119</xmin>
			<ymin>2240</ymin>
			<xmax>1183</xmax>
			<ymax>2304</ymax>
		</bndbox>
	</object>
	<object>
		<name>WF</name>
		<pose>Unspecified</pose>
		<truncated>0</truncated>
		<difficult>0</difficult>
		<bndbox>
			<xmin>1492</xmin>
			<ymin>2217</ymin>
			<xmax>1556</xmax>
			<ymax>2281</ymax>
		</bndbox>
	</object>
	<object>
		<name>WF</name>
		<pose>Unspecified</pose>
		<truncated>0</truncated>
		<difficult>0</difficult>
		<bndbox>
			<xmin>904</xmin>
			<ymin>1986</ymin>
			<xmax>968</xmax>
			<ymax>2050</ymax>
		</bndbox>
	</object>
	<object>
		<name>WF</name>
		<pose>Unspecified</pose>
		<truncated>0</truncated>
		<difficult>0</difficult>
		<bndbox>
			<xmin>708</xmin>
			<ymin>1999</ymin>
			<xmax>772</xmax>
			<ymax>2063</ymax>
		</bndbox>
	</object>
	<object>
		<name>WF</name>
		<pose>Unspecified</pose>
		<truncated>0</truncated>
		<difficult>0</difficult>
		<bndbox>
			<xmin>632</xmin>
			<ymin>1932</ymin>
			<xmax>696</xmax>
			<ymax>1996</ymax>
		</bndbox>
	</object>
	<object>
		<name>WF</name>
		<pose>Unspecified</pose>
		<truncated>0</truncated>
		<difficult>0</difficult>
		<bndbox>
			<xmin>233</xmin>
			<ymin>1978</ymin>
			<xmax>297</xmax>
			<ymax>2042</ymax>
		</bndbox>
	</object>
	<object>
		<name>WF</name>
		<pose>Unspecified</pose>
		<truncated>0</truncated>
		<difficult>0</difficult>
		<bndbox>
			<xmin>1697</xmin>
			<ymin>2657</ymin>
			<xmax>1761</xmax>
			<ymax>2721</ymax>
		</bndbox>
	</object>
	<object>
		<name>WF</name>
		<pose>Unspecified</pose>
		<truncated>0</truncated>
		<difficult>0</difficult>
		<bndbox>
			<xmin>1581</xmin>
			<ymin>2083</ymin>
			<xmax>1645</xmax>
			<ymax>2147</ymax>
		</bndbox>
	</object>
	<object>
		<name>WF</name>
		<pose>Unspecified</pose>
		<truncated>0</truncated>
		<difficult>0</difficult>
		<bndbox>
			<xmin>897</xmin>
			<ymin>2744</ymin>
			<xmax>961</xmax>
			<ymax>2808</ymax>
		</bndbox>
	</object>
	<object>
		<name>WF</name>
		<pose>Unspecified</pose>
		<truncated>0</truncated>
		<difficult>0</difficult>
		<bndbox>
			<xmin>1068</xmin>
			<ymin>2696</ymin>
			<xmax>1132</xmax>
			<ymax>2760</ymax>
		</bndbox>
	</object>
	<object>
		<name>WF</name>
		<pose>Unspecified</pose>
		<truncated>0</truncated>
		<difficult>0</difficult>
		<bndbox>
			<xmin>607</xmin>
			<ymin>2730</ymin>
			<xmax>671</xmax>
			<ymax>2794</ymax>
		</bndbox>
	</object>
	<object>
		<name>WF</name>
		<pose>Unspecified</pose>
		<truncated>0</truncated>
		<difficult>0</difficult>
		<bndbox>
			<xmin>2823</xmin>
			<ymin>1972</ymin>
			<xmax>2887</xmax>
			<ymax>2036</ymax>
		</bndbox>
	</object>
	<object>
		<name>WF</name>
		<pose>Unspecified</pose>
		<truncated>0</truncated>
		<difficult>0</difficult>
		<bndbox>
			<xmin>2561</xmin>
			<ymin>2278</ymin>
			<xmax>2625</xmax>
			<ymax>2342</ymax>
		</bndbox>
	</object>
	<object>
		<name>WF</name>
		<pose>Unspecified</pose>
		<truncated>0</truncated>
		<difficult>0</difficult>
		<bndbox>
			<xmin>2634</xmin>
			<ymin>2614</ymin>
			<xmax>2698</xmax>
			<ymax>2678</ymax>
		</bndbox>
	</object>
	<object>
		<name>WF</name>
		<pose>Unspecified</pose>
		<truncated>0</truncated>
		<difficult>0</difficult>
		<bndbox>
			<xmin>3310</xmin>
			<ymin>2803</ymin>
			<xmax>3374</xmax>
			<ymax>2867</ymax>
		</bndbox>
	</object>
	<object>
		<name>WF</name>
		<pose>Unspecified</pose>
		<truncated>0</truncated>
		<difficult>0</difficult>
		<bndbox>
			<xmin>1798</xmin>
			<ymin>2026</ymin>
			<xmax>1862</xmax>
			<ymax>2090</ymax>
		</bndbox>
	</object>
	<object>
		<name>WF</name>
		<pose>Unspecified</pose>
		<truncated>0</truncated>
		<difficult>0</difficult>
		<bndbox>
			<xmin>3672</xmin>
			<ymin>2046</ymin>
			<xmax>3736</xmax>
			<ymax>2110</ymax>
		</bndbox>
	</object>
	<object>
		<name>WF</name>
		<pose>Unspecified</pose>
		<truncated>0</truncated>
		<difficult>0</difficult>
		<bndbox>
			<xmin>4760</xmin>
			<ymin>2178</ymin>
			<xmax>4824</xmax>
			<ymax>2242</ymax>
		</bndbox>
	</object>
</annotation>