<?xml version="1.0" encoding="utf-8"?>
<annotation>
	<folder>--</folder>
	<filename>--</filename>
	<path>--</path>
	<source>
		<database>Unknown</database>
	</source>
	<size>
		<width>3456</width>
		<height>5184</height>
	</size>
	<segmented>3</segmented>
	<object>
		<name>WF</name>
		<pose>Unspecified</pose>
		<truncated>0</truncated>
		<difficult>0</difficult>
		<bndbox>
			<xmin>1317</xmin>
			<ymin>1914</ymin>
			<xmax>1369</xmax>
			<ymax>1964</ymax>
		</bndbox>
	</object>
	<object>
		<name>WF</name>
		<pose>Unspecified</pose>
		<truncated>0</truncated>
		<difficult>0</difficult>
		<bndbox>
			<xmin>1603</xmin>
			<ymin>2277</ymin>
			<xmax>1657</xmax>
			<ymax>2333</ymax>
		</bndbox>
	</object>
</annotation>